[
 {
  "id": "status-210420000",
  "type": "vessel_status",
  "mmsi": 210420000,
  "name": "ANGKALIA",
  "lat": 37.933165,
  "lon": 23.679775,
  "time_utc": "2026-07-14T02:31:57+00:00",
  "text": "ANGKALIA (pleasure) is stationary at 4 km off Piraeus. Reported destination: FLISVOS."
 },
 {
  "id": "status-212769000",
  "type": "vessel_status",
  "mmsi": 212769000,
  "name": "MAGIC 3",
  "lat": 37.94352333333333,
  "lon": 23.643106666666664,
  "time_utc": "2026-07-14T02:31:57+00:00",
  "text": "MAGIC 3 (high-speed craft) is stationary at Piraeus. Reported destination: ARGOSARONIKOS."
 },
 {
  "id": "status-212912000",
  "type": "vessel_status",
  "mmsi": 212912000,
  "name": "EUROCHAMPION JET",
  "lat": 37.94168666666667,
  "lon": 23.6402,
  "time_utc": "2026-07-14T02:31:57+00:00",
  "text": "EUROCHAMPION JET (high-speed craft) is stationary at Piraeus. Reported destination: P.P.N.K.K.K.N.P.P."
 },
 {
  "id": "status-232014927",
  "type": "vessel_status",
  "mmsi": 232014927,
  "name": "YOUNAN",
  "lat": 37.931165,
  "lon": 23.683361666666666,
  "time_utc": "2026-07-14T02:31:57+00:00",
  "text": "YOUNAN (pleasure) is stationary at 4 km off Piraeus."
 },
 {
  "id": "status-232049174",
  "type": "vessel_status",
  "mmsi": 232049174,
  "name": "CHARISMA",
  "lat": 37.932098333333336,
  "lon": 23.647066666666667,
  "time_utc": "2026-07-14T02:31:57+00:00",
  "text": "CHARISMA (pleasure) is stationary at Piraeus. Reported destination: ZEA."
 },
 {
  "id": "status-237006500",
  "type": "vessel_status",
  "mmsi": 237006500,
  "name": "DIMITRIOS",
  "lat": 38.03339833333334,
  "lon": 23.59043,
  "time_utc": "2026-07-14T02:31:57+00:00",
  "text": "DIMITRIOS (cargo) is stationary at 4 km off Elefsina. Reported destination: GRASS."
 },
 {
  "id": "status-237009900",
  "type": "vessel_status",
  "mmsi": 237009900,
  "name": "MELINA II",
  "lat": 38.0357,
  "lon": 23.552,
  "time_utc": "2026-07-14T02:31:57+00:00",
  "text": "MELINA II (cargo) is moored at Elefsina. Reported destination: ELEUSINA."
 },
 {
  "id": "status-237697600",
  "type": "vessel_status",
  "mmsi": 237697600,
  "name": "O'RION",
  "lat": 37.9116,
  "lon": 23.70249,
  "time_utc": "2026-07-14T02:31:57+00:00",
  "text": "O'RION (pleasure) is stationary at 7 km off Piraeus. Reported destination: ALIMOS."
 },
 {
  "id": "status-239924000",
  "type": "vessel_status",
  "mmsi": 239924000,
  "name": "BLUE STAR PAROS",
  "lat": 37.94855,
  "lon": 23.6405,
  "time_utc": "2026-07-14T02:31:57+00:00",
  "text": "BLUE STAR PAROS (passenger) is moored at Piraeus. Reported destination: PIR SYR TIN MYK."
 },
 {
  "id": "status-240039100",
  "type": "vessel_status",
  "mmsi": 240039100,
  "name": "CAPTAIN DIAMANTIS",
  "lat": 38.02948333333333,
  "lon": 23.5319,
  "time_utc": "2026-07-14T02:31:57+00:00",
  "text": "CAPTAIN DIAMANTIS (cargo) is stationary at Elefsina. Reported destination: ELEFSINA."
 },
 {
  "id": "status-240137000",
  "type": "vessel_status",
  "mmsi": 240137000,
  "name": "ILIAS R",
  "lat": 37.95766166666667,
  "lon": 23.611368333333335,
  "time_utc": "2026-07-14T02:31:57+00:00",
  "text": "ILIAS R (fishing) is underway at 0 knots near 3 km off Piraeus, heading east. Reported destination: CHANIA."
 },
 {
  "id": "status-240191100",
  "type": "vessel_status",
  "mmsi": 240191100,
  "name": "GLYKOFILOUSA VIII",
  "lat": 37.96105333333333,
  "lon": 23.552145,
  "time_utc": "2026-07-14T02:31:57+00:00",
  "text": "GLYKOFILOUSA VIII (passenger) is underway at 7 knots near 1 km off Perama, heading west. Reported destination: SALAMINA-PERAMA."
 },
 {
  "id": "status-240418200",
  "type": "vessel_status",
  "mmsi": 240418200,
  "name": "SUPPORTER",
  "lat": 37.944885,
  "lon": 23.615711666666666,
  "time_utc": "2026-07-14T02:31:57+00:00",
  "text": "SUPPORTER (special craft) is stationary at 2 km off Piraeus. Reported destination: PERIOCHI."
 },
 {
  "id": "status-240580000",
  "type": "vessel_status",
  "mmsi": 240580000,
  "name": "ARIADNE",
  "lat": 37.6975,
  "lon": 23.77713333333333,
  "time_utc": "2026-07-14T02:31:57+00:00",
  "text": "ARIADNE (passenger) is underway at 21 knots near open water (37.697, 23.777), heading northwest. Reported destination: GRPIR."
 },
 {
  "id": "status-240667400",
  "type": "vessel_status",
  "mmsi": 240667400,
  "name": "ANASTASIA K III",
  "lat": 37.96060666666666,
  "lon": 23.57152166666667,
  "time_utc": "2026-07-14T02:31:57+00:00",
  "text": "ANASTASIA K III (cargo) is stationary at Perama. Reported destination: ELEFSINA."
 },
 {
  "id": "status-240871000",
  "type": "vessel_status",
  "mmsi": 240871000,
  "name": "ECOBREEZE",
  "lat": 38.03709,
  "lon": 23.533243333333335,
  "time_utc": "2026-07-14T02:31:57+00:00",
  "text": "ECOBREEZE (tanker) is stationary at Elefsina."
 },
 {
  "id": "status-240897000",
  "type": "vessel_status",
  "mmsi": 240897000,
  "name": "AEGEAN ACE",
  "lat": 38.03744,
  "lon": 23.533586666666668,
  "time_utc": "2026-07-14T02:31:57+00:00",
  "text": "AEGEAN ACE (tanker) is stationary at Elefsina. Reported destination: PERIOHI."
 },
 {
  "id": "status-240985000",
  "type": "vessel_status",
  "mmsi": 240985000,
  "name": "RHINO",
  "lat": 37.94699,
  "lon": 23.555515,
  "time_utc": "2026-07-14T02:31:57+00:00",
  "text": "RHINO (cargo) is stationary at 2 km off Perama. Reported destination: GRSAL."
 },
 {
  "id": "status-241192800",
  "type": "vessel_status",
  "mmsi": 241192800,
  "name": "CAPTAIN VAGGELIS Z",
  "lat": 38.03614833333334,
  "lon": 23.508895,
  "time_utc": "2026-07-14T02:31:57+00:00",
  "text": "CAPTAIN VAGGELIS Z (tug/tow) is stationary at Elefsis Bay anchorage."
 },
 {
  "id": "status-241324000",
  "type": "vessel_status",
  "mmsi": 241324000,
  "name": "ERATO",
  "lat": 37.92031833333333,
  "lon": 23.551835,
  "time_utc": "2026-07-14T02:31:57+00:00",
  "text": "ERATO (tanker) is stationary at Piraeus anchorage. Reported destination: GRPIR."
 },
 {
  "id": "status-241588000",
  "type": "vessel_status",
  "mmsi": 241588000,
  "name": "CHRISTOS XLVI",
  "lat": 37.95363833333333,
  "lon": 23.551558333333332,
  "time_utc": "2026-07-14T02:31:57+00:00",
  "text": "CHRISTOS XLVI (special craft) is stationary at 2 km off Perama. Reported destination: PIRAEUS."
 },
 {
  "id": "status-241872000",
  "type": "vessel_status",
  "mmsi": 241872000,
  "name": "VERNICOS SCAFI III",
  "lat": 37.93462666666667,
  "lon": 23.62304,
  "time_utc": "2026-07-14T02:31:57+00:00",
  "text": "VERNICOS SCAFI III (special craft) is stationary at Piraeus. Reported destination: PIRAEUS."
 },
 {
  "id": "status-241911000",
  "type": "vessel_status",
  "mmsi": 241911000,
  "name": "CAPTAIN GIANNIS P.",
  "lat": 37.943755,
  "lon": 23.631973333333335,
  "time_utc": "2026-07-14T02:31:57+00:00",
  "text": "CAPTAIN GIANNIS P. (special craft) is stationary at Piraeus. Reported destination: GRPIR."
 },
 {
  "id": "status-241926000",
  "type": "vessel_status",
  "mmsi": 241926000,
  "name": "LYBOUSSAKIS ATLAS",
  "lat": 37.95741666666667,
  "lon": 23.61027,
  "time_utc": "2026-07-14T02:31:57+00:00",
  "text": "LYBOUSSAKIS ATLAS (special craft) is stationary at 3 km off Piraeus. Reported destination: PIRAEUS."
 },
 {
  "id": "status-241951000",
  "type": "vessel_status",
  "mmsi": 241951000,
  "name": "SVS II",
  "lat": 37.88601666666667,
  "lon": 23.549411666666668,
  "time_utc": "2026-07-14T02:31:57+00:00",
  "text": "SVS II (tug/tow) is underway at 10 knots near Piraeus anchorage, heading northeast. Reported destination: PIRAEUS."
 },
 {
  "id": "status-241975000",
  "type": "vessel_status",
  "mmsi": 241975000,
  "name": "LYBOUSSAKIS TAXIARCH",
  "lat": 37.957348333333336,
  "lon": 23.610551666666666,
  "time_utc": "2026-07-14T02:31:57+00:00",
  "text": "LYBOUSSAKIS TAXIARCH (special craft) is stationary at 3 km off Piraeus. Reported destination: KERATSINI."
 },
 {
  "id": "status-247048150",
  "type": "vessel_status",
  "mmsi": 247048150,
  "name": "BOUKI",
  "lat": 37.93091666666667,
  "lon": 23.684263333333334,
  "time_utc": "2026-07-14T02:31:57+00:00",
  "text": "BOUKI is stationary at 4 km off Piraeus."
 },
 {
  "id": "status-247271400",
  "type": "vessel_status",
  "mmsi": 247271400,
  "name": "MAGNIFICA",
  "lat": 37.880916666666664,
  "lon": 23.53101666666667,
  "time_utc": "2026-07-14T02:31:57+00:00",
  "text": "MAGNIFICA (tanker) is at anchor at Piraeus anchorage. Reported destination: GR PIR."
 },
 {
  "id": "status-248663000",
  "type": "vessel_status",
  "mmsi": 248663000,
  "name": "ZEFIRA",
  "lat": 37.80780333333333,
  "lon": 23.811210000000003,
  "time_utc": "2026-07-14T02:31:57+00:00",
  "text": "ZEFIRA (pleasure) is at anchor at open water (37.808, 23.811). Reported destination: ORMOS VARIS."
 },
 {
  "id": "status-249373000",
  "type": "vessel_status",
  "mmsi": 249373000,
  "name": "MIA RAMA",
  "lat": 37.93874166666667,
  "lon": 23.66856,
  "time_utc": "2026-07-14T02:31:57+00:00",
  "text": "MIA RAMA (pleasure) is moored at 3 km off Piraeus. Reported destination: ATHENS MARINA."
 },
 {
  "id": "status-249410000",
  "type": "vessel_status",
  "mmsi": 249410000,
  "name": "RINI",
  "lat": 37.93197333333333,
  "lon": 23.68223,
  "time_utc": "2026-07-14T02:31:57+00:00",
  "text": "RINI is stationary at 4 km off Piraeus."
 },
 {
  "id": "status-256027000",
  "type": "vessel_status",
  "mmsi": 256027000,
  "name": "SOUNION II",
  "lat": 38.036295,
  "lon": 23.500113333333335,
  "time_utc": "2026-07-14T02:31:57+00:00",
  "text": "SOUNION II (pleasure) is stationary at Elefsis Bay anchorage."
 },
 {
  "id": "status-256911000",
  "type": "vessel_status",
  "mmsi": 256911000,
  "name": "MADO",
  "lat": 37.911658333333335,
  "lon": 23.702328333333334,
  "time_utc": "2026-07-14T02:31:57+00:00",
  "text": "MADO is moored at 7 km off Piraeus."
 },
 {
  "id": "status-319314500",
  "type": "vessel_status",
  "mmsi": 319314500,
  "name": "TFB 1",
  "lat": 37.93165333333333,
  "lon": 23.680076666666665,
  "time_utc": "2026-07-14T02:31:57+00:00",
  "text": "TFB 1 (pleasure) was last heard near 4 km off Piraeus."
 },
 {
  "id": "status-636011267",
  "type": "vessel_status",
  "mmsi": 636011267,
  "name": "MARIANNA V.V.",
  "lat": 37.85678333333333,
  "lon": 23.534266666666667,
  "time_utc": "2026-07-14T02:31:57+00:00",
  "text": "MARIANNA V.V. (tanker) is at anchor at open water (37.857, 23.534). Reported destination: GR PIR."
 },
 {
  "id": "status-636022701",
  "type": "vessel_status",
  "mmsi": 636022701,
  "name": "DELTA IOS",
  "lat": 37.850166666666674,
  "lon": 23.521133333333335,
  "time_utc": "2026-07-14T02:31:57+00:00",
  "text": "DELTA IOS (tanker) is at anchor at open water (37.850, 23.521). Reported destination: PIRAEUS."
 },
 {
  "id": "status-207838290",
  "type": "vessel_status",
  "mmsi": 207838290,
  "name": "BELLA VITA",
  "lat": 37.94176,
  "lon": 23.670328333333334,
  "time_utc": "2026-07-14T02:31:57+00:00",
  "text": "BELLA VITA (pleasure) was last heard near 3 km off Piraeus."
 },
 {
  "id": "status-209395000",
  "type": "vessel_status",
  "mmsi": 209395000,
  "name": "WORLDCHAMPION JET",
  "lat": 37.945125,
  "lon": 23.639898333333335,
  "time_utc": "2026-07-14T02:31:57+00:00",
  "text": "WORLDCHAMPION JET (high-speed craft) is moored at Piraeus. Reported destination: P-S-T-M-P-N-T-H."
 },
 {
  "id": "status-210205000",
  "type": "vessel_status",
  "mmsi": 210205000,
  "name": "EXPRESS JET",
  "lat": 37.940205,
  "lon": 23.639216666666666,
  "time_utc": "2026-07-14T02:31:57+00:00",
  "text": "EXPRESS JET (high-speed craft) is stationary at Piraeus. Reported destination: P-P-N-K-N-P-P."
 },
 {
  "id": "status-210551000",
  "type": "vessel_status",
  "mmsi": 210551000,
  "name": "ALIA",
  "lat": 37.94122166666667,
  "lon": 23.670503333333333,
  "time_utc": "2026-07-14T02:31:57+00:00",
  "text": "ALIA is stationary at 3 km off Piraeus."
 },
 {
  "id": "status-232067430",
  "type": "vessel_status",
  "mmsi": 232067430,
  "name": "ALWASEEM",
  "lat": 37.931535000000004,
  "lon": 23.650105,
  "time_utc": "2026-07-14T02:31:57+00:00",
  "text": "ALWASEEM is stationary at Piraeus."
 },
 {
  "id": "status-235096584",
  "type": "vessel_status",
  "mmsi": 235096584,
  "name": "BLEU BLANC",
  "lat": 37.932741666666665,
  "lon": 23.682358333333333,
  "time_utc": "2026-07-14T02:31:57+00:00",
  "text": "BLEU BLANC is stationary at 4 km off Piraeus."
 },
 {
  "id": "status-237640000",
  "type": "vessel_status",
  "mmsi": 237640000,
  "name": "LITHI",
  "lat": 37.940936666666666,
  "lon": 23.670345,
  "time_utc": "2026-07-14T02:31:57+00:00",
  "text": "LITHI (pleasure) is moored at 3 km off Piraeus."
 },
 {
  "id": "status-237746400",
  "type": "vessel_status",
  "mmsi": 237746400,
  "name": "THEOMITOR",
  "lat": 37.965111666666665,
  "lon": 23.529345,
  "time_utc": "2026-07-14T02:31:57+00:00",
  "text": "THEOMITOR (passenger) is stationary at Salamina (Paloukia). Reported destination: PALOUKIA-PERAMA."
 },
 {
  "id": "status-239784800",
  "type": "vessel_status",
  "mmsi": 239784800,
  "name": "NAVASOL",
  "lat": 37.91507,
  "lon": 23.701438333333332,
  "time_utc": "2026-07-14T02:31:57+00:00",
  "text": "NAVASOL is stationary at 6 km off Piraeus."
 },
 {
  "id": "status-239998600",
  "type": "vessel_status",
  "mmsi": 239998600,
  "name": "ACCORD",
  "lat": 38.029316666666666,
  "lon": 23.561183333333336,
  "time_utc": "2026-07-14T02:31:57+00:00",
  "text": "ACCORD (tanker) is stationary at 2 km off Elefsina. Reported destination: ELEFSIS."
 },
 {
  "id": "status-240004600",
  "type": "vessel_status",
  "mmsi": 240004600,
  "name": "SOLE DI MARE",
  "lat": 37.93250833333333,
  "lon": 23.64765,
  "time_utc": "2026-07-14T02:31:57+00:00",
  "text": "SOLE DI MARE (pleasure) is moored at Piraeus. Reported destination: ZEA."
 },
 {
  "id": "status-240013900",
  "type": "vessel_status",
  "mmsi": 240013900,
  "name": "STRATOS",
  "lat": 38.029048333333336,
  "lon": 23.5957,
  "time_utc": "2026-07-14T02:31:57+00:00",
  "text": "STRATOS (special craft) is stationary at 5 km off Elefsina. Reported destination: PIRAEUS."
 },
 {
  "id": "status-240151600",
  "type": "vessel_status",
  "mmsi": 240151600,
  "name": "CHRISTOS XLV",
  "lat": 37.960675,
  "lon": 23.556843333333333,
  "time_utc": "2026-07-14T02:31:57+00:00",
  "text": "CHRISTOS XLV (special craft) is stationary at 1 km off Perama. Reported destination: PERAMA."
 },
 {
  "id": "status-240323500",
  "type": "vessel_status",
  "mmsi": 240323500,
  "name": "CONDOR A",
  "lat": 37.93298666666667,
  "lon": 23.648196666666667,
  "time_utc": "2026-07-14T02:31:57+00:00",
  "text": "CONDOR A (pleasure) is stationary at Piraeus. Reported destination: AGIOS KOSMAS."
 },
 {
  "id": "status-240564300",
  "type": "vessel_status",
  "mmsi": 240564300,
  "name": "EXPLORION",
  "lat": 37.93846,
  "lon": 23.647901666666666,
  "time_utc": "2026-07-14T02:31:57+00:00",
  "text": "EXPLORION (pleasure) is stationary at Piraeus."
 },
 {
  "id": "status-240620300",
  "type": "vessel_status",
  "mmsi": 240620300,
  "name": "GEORGIA G",
  "lat": 38.02870333333333,
  "lon": 23.594105000000003,
  "time_utc": "2026-07-14T02:31:57+00:00",
  "text": "GEORGIA G (tanker) is stationary at 5 km off Elefsina. Reported destination: PERIOXI."
 },
 {
  "id": "status-240806000",
  "type": "vessel_status",
  "mmsi": 240806000,
  "name": "VERA",
  "lat": 37.93814333333333,
  "lon": 23.668203333333334,
  "time_utc": "2026-07-14T02:31:57+00:00",
  "text": "VERA (pleasure) is stationary at 3 km off Piraeus. Reported destination: SARONIKOS."
 },
 {
  "id": "status-240922000",
  "type": "vessel_status",
  "mmsi": 240922000,
  "name": "PROTUG 17",
  "lat": 37.950048333333335,
  "lon": 23.607031666666668,
  "time_utc": "2026-07-14T02:31:57+00:00",
  "text": "PROTUG 17 (special craft) is stationary at 3 km off Piraeus. Reported destination: DRAPETSONA-PIRAEUS."
 },
 {
  "id": "status-241728000",
  "type": "vessel_status",
  "mmsi": 241728000,
  "name": "PANORMITIS",
  "lat": 37.95865166666667,
  "lon": 23.61312,
  "time_utc": "2026-07-14T02:31:57+00:00",
  "text": "PANORMITIS (special craft) is stationary at 3 km off Piraeus. Reported destination: PIRAEUS."
 },
 {
  "id": "status-241903000",
  "type": "vessel_status",
  "mmsi": 241903000,
  "name": "DON'T WORRY",
  "lat": 37.94090833333333,
  "lon": 23.67039,
  "time_utc": "2026-07-14T02:31:57+00:00",
  "text": "DON'T WORRY (pleasure) is stationary at 3 km off Piraeus. Reported destination: PIRAEUS."
 },
 {
  "id": "status-241927000",
  "type": "vessel_status",
  "mmsi": 241927000,
  "name": "SVS I",
  "lat": 38.036053333333335,
  "lon": 23.513901666666666,
  "time_utc": "2026-07-14T02:31:57+00:00",
  "text": "SVS I (special craft) is stationary at Elefsis Bay anchorage. Reported destination: PIRAEUS."
 },
 {
  "id": "status-248624000",
  "type": "vessel_status",
  "mmsi": 248624000,
  "name": "BARACUDA VALLETTA",
  "lat": 37.931551666666664,
  "lon": 23.64984666666667,
  "time_utc": "2026-07-14T02:31:57+00:00",
  "text": "BARACUDA VALLETTA is moored at Piraeus."
 },
 {
  "id": "status-256002020",
  "type": "vessel_status",
  "mmsi": 256002020,
  "name": "SHALIMAR II",
  "lat": 37.931325,
  "lon": 23.68043833333333,
  "time_utc": "2026-07-14T02:31:57+00:00",
  "text": "SHALIMAR II is stationary at 4 km off Piraeus."
 },
 {
  "id": "status-256002201",
  "type": "vessel_status",
  "mmsi": 256002201,
  "name": "BOLARO",
  "lat": 37.93267166666667,
  "lon": 23.67990166666667,
  "time_utc": "2026-07-14T02:31:57+00:00",
  "text": "BOLARO is stationary at 4 km off Piraeus."
 },
 {
  "id": "status-256003488",
  "type": "vessel_status",
  "mmsi": 256003488,
  "name": "PANAGIA RODON TO AMA",
  "lat": 37.93202833333333,
  "lon": 23.682843333333334,
  "time_utc": "2026-07-14T02:31:57+00:00",
  "text": "PANAGIA RODON TO AMA is stationary at 4 km off Piraeus."
 },
 {
  "id": "status-305037300",
  "type": "vessel_status",
  "mmsi": 305037300,
  "name": "CABO",
  "lat": 37.95038833333333,
  "lon": 23.547505,
  "time_utc": "2026-07-14T02:31:57+00:00",
  "text": "CABO (passenger) is moored at 2 km off Salamina (Paloukia). Reported destination: GRPIR."
 },
 {
  "id": "status-319322200",
  "type": "vessel_status",
  "mmsi": 319322200,
  "name": "NORFOLK STAR",
  "lat": 37.81172,
  "lon": 23.807331666666666,
  "time_utc": "2026-07-14T02:31:57+00:00",
  "text": "NORFOLK STAR (sailing) is at anchor at open water (37.812, 23.807). Reported destination: ATHENS."
 },
 {
  "id": "status-370608000",
  "type": "vessel_status",
  "mmsi": 370608000,
  "name": "M/Y TRIDENT I",
  "lat": 37.96044666666667,
  "lon": 23.57099,
  "time_utc": "2026-07-14T02:31:57+00:00",
  "text": "M/Y TRIDENT I (pleasure) is stationary at Perama. Reported destination: ELGOUNA/MARINA."
 },
 {
  "id": "status-538007935",
  "type": "vessel_status",
  "mmsi": 538007935,
  "name": "ALIKI FORCE",
  "lat": 38.029016666666664,
  "lon": 23.497133333333334,
  "time_utc": "2026-07-14T02:31:57+00:00",
  "text": "ALIKI FORCE (cargo) is moored at Elefsis Bay anchorage. Reported destination: GRELE."
 },
 {
  "id": "status-605016420",
  "type": "vessel_status",
  "mmsi": 605016420,
  "name": "BADJI MOKHTAR III",
  "lat": 38.028463333333335,
  "lon": 23.497338333333335,
  "time_utc": "2026-07-14T02:31:57+00:00",
  "text": "BADJI MOKHTAR III (passenger) is stationary at Elefsis Bay anchorage. Reported destination: GRE ELEFSIS."
 },
 {
  "id": "status-237500621",
  "type": "vessel_status",
  "mmsi": 237500621,
  "name": "IGNATIOS XXI",
  "lat": 37.93445,
  "lon": 23.618201666666668,
  "time_utc": "2026-07-14T02:31:57+00:00",
  "text": "IGNATIOS XXI is stationary at Piraeus."
 },
 {
  "id": "status-237838900",
  "type": "vessel_status",
  "mmsi": 237838900,
  "name": "IONIA",
  "lat": 37.93799,
  "lon": 23.685836666666667,
  "time_utc": "2026-07-14T02:31:57+00:00",
  "text": "IONIA is stationary at 4 km off Piraeus."
 },
 {
  "id": "status-239951600",
  "type": "vessel_status",
  "mmsi": 239951600,
  "name": "HYDRA VIII",
  "lat": 37.91329333333333,
  "lon": 23.705568333333336,
  "time_utc": "2026-07-14T02:31:57+00:00",
  "text": "HYDRA VIII (pleasure) is stationary at 7 km off Piraeus."
 },
 {
  "id": "status-240170200",
  "type": "vessel_status",
  "mmsi": 240170200,
  "name": "SPIRIT L",
  "lat": 37.932339999999996,
  "lon": 23.647086666666667,
  "time_utc": "2026-07-14T02:31:57+00:00",
  "text": "SPIRIT L (pleasure) is moored at Piraeus."
 },
 {
  "id": "status-240601400",
  "type": "vessel_status",
  "mmsi": 240601400,
  "name": "SEA YA",
  "lat": 37.93085333333333,
  "lon": 23.684306666666664,
  "time_utc": "2026-07-14T02:31:57+00:00",
  "text": "SEA YA is stationary at 4 km off Piraeus."
 },
 {
  "id": "status-240708000",
  "type": "vessel_status",
  "mmsi": 240708000,
  "name": "AEGEAN III",
  "lat": 38.03722666666667,
  "lon": 23.533135,
  "time_utc": "2026-07-14T02:31:57+00:00",
  "text": "AEGEAN III (tanker) is moored at Elefsina. Reported destination: PERIOHI."
 },
 {
  "id": "status-241925000",
  "type": "vessel_status",
  "mmsi": 241925000,
  "name": "CHRISTOS 73",
  "lat": 37.95226666666667,
  "lon": 23.551945,
  "time_utc": "2026-07-14T02:31:57+00:00",
  "text": "CHRISTOS 73 (special craft) is stationary at 2 km off Perama. Reported destination: GRPER."
 },
 {
  "id": "status-248472000",
  "type": "vessel_status",
  "mmsi": 248472000,
  "name": "SIDER LION",
  "lat": 38.014745,
  "lon": 23.519836666666667,
  "time_utc": "2026-07-14T02:31:57+00:00",
  "text": "SIDER LION (cargo) is at anchor at 3 km off Elefsina. Reported destination: GREEU."
 },
 {
  "id": "status-319289600",
  "type": "vessel_status",
  "mmsi": 319289600,
  "name": "DARLIN",
  "lat": 37.33999166666667,
  "lon": 23.436231666666668,
  "time_utc": "2026-07-14T02:31:57+00:00",
  "text": "DARLIN is stationary at 3 km off Hydra. Reported destination: PALERMO."
 },
 {
  "id": "status-511100847",
  "type": "vessel_status",
  "mmsi": 511100847,
  "name": "CORAL",
  "lat": 37.936793333333334,
  "lon": 23.649929999999998,
  "time_utc": "2026-07-14T02:31:57+00:00",
  "text": "CORAL is stationary at Piraeus."
 },
 {
  "id": "status-636024002",
  "type": "vessel_status",
  "mmsi": 636024002,
  "name": "MINERVA VIRGO",
  "lat": 38.00560333333333,
  "lon": 23.590885,
  "time_utc": "2026-07-14T02:31:57+00:00",
  "text": "MINERVA VIRGO (tanker) is moored at 5 km off Perama. Reported destination: FOR_ORDERS."
 },
 {
  "id": "status-210977000",
  "type": "vessel_status",
  "mmsi": 210977000,
  "name": "TERA JET 2",
  "lat": 38.022465000000004,
  "lon": 24.011338333333335,
  "time_utc": "2026-07-14T02:31:57+00:00",
  "text": "TERA JET 2 (high-speed craft) is stationary at Rafina. Reported destination: RATMPMTAR."
 },
 {
  "id": "status-237512300",
  "type": "vessel_status",
  "mmsi": 237512300,
  "name": "S/Y NEMESIS",
  "lat": 37.93850666666666,
  "lon": 23.686513333333334,
  "time_utc": "2026-07-14T02:31:57+00:00",
  "text": "S/Y NEMESIS is stationary at 4 km off Piraeus."
 },
 {
  "id": "status-238730740",
  "type": "vessel_status",
  "mmsi": 238730740,
  "name": "HYRPUS",
  "lat": 37.92939666666667,
  "lon": 23.684696666666664,
  "time_utc": "2026-07-14T02:31:57+00:00",
  "text": "HYRPUS (pleasure) is moored at 4 km off Piraeus. Reported destination: FLISVOS."
 },
 {
  "id": "status-240334100",
  "type": "vessel_status",
  "mmsi": 240334100,
  "name": "OVAL",
  "lat": 37.93378166666666,
  "lon": 23.64891,
  "time_utc": "2026-07-14T02:31:57+00:00",
  "text": "OVAL (pleasure) is moored at Piraeus. Reported destination: ZEA."
 },
 {
  "id": "status-240369400",
  "type": "vessel_status",
  "mmsi": 240369400,
  "name": "LOCO 13",
  "lat": 37.91407166666667,
  "lon": 23.701968333333333,
  "time_utc": "2026-07-14T02:31:57+00:00",
  "text": "LOCO 13 (pleasure) is moored at 7 km off Piraeus."
 },
 {
  "id": "status-241782000",
  "type": "vessel_status",
  "mmsi": 241782000,
  "name": "ALMYRA II",
  "lat": 37.93096166666667,
  "lon": 23.680513333333334,
  "time_utc": "2026-07-14T02:31:57+00:00",
  "text": "ALMYRA II (pleasure) is moored at 4 km off Piraeus. Reported destination: FLISVOS MARINA."
 },
 {
  "id": "status-538008770",
  "type": "vessel_status",
  "mmsi": 538008770,
  "name": "GLOBAL FORTUNE",
  "lat": 37.89722166666666,
  "lon": 23.535356666666665,
  "time_utc": "2026-07-14T02:31:57+00:00",
  "text": "GLOBAL FORTUNE (cargo) is at anchor at Piraeus anchorage. Reported destination: GRPIR."
 },
 {
  "id": "status-636013764",
  "type": "vessel_status",
  "mmsi": 636013764,
  "name": "FELIX",
  "lat": 37.94929833333333,
  "lon": 23.598711666666667,
  "time_utc": "2026-07-14T02:31:57+00:00",
  "text": "FELIX (tanker) is moored at 3 km off Perama. Reported destination: GR PIR."
 },
 {
  "id": "status-667002548",
  "type": "vessel_status",
  "mmsi": 667002548,
  "name": "CANOPUS S",
  "lat": 37.892205,
  "lon": 23.541018333333334,
  "time_utc": "2026-07-14T02:31:57+00:00",
  "text": "CANOPUS S (cargo) is at anchor at Piraeus anchorage. Reported destination: AL DRZ."
 },
 {
  "id": "status-237296900",
  "type": "vessel_status",
  "mmsi": 237296900,
  "name": "EVGENIA",
  "lat": 37.26819,
  "lon": 23.157856666666664,
  "time_utc": "2026-07-14T02:31:57+00:00",
  "text": "EVGENIA is underway at 1 knots near Spetses, heading east."
 },
 {
  "id": "status-240123500",
  "type": "vessel_status",
  "mmsi": 240123500,
  "name": "DELTA",
  "lat": 37.91263333333333,
  "lon": 23.702144999999998,
  "time_utc": "2026-07-14T02:31:57+00:00",
  "text": "DELTA (sailing) is stationary at 7 km off Piraeus."
 },
 {
  "id": "status-241633000",
  "type": "vessel_status",
  "mmsi": 241633000,
  "name": "ECOGEMINI",
  "lat": 37.94924666666667,
  "lon": 23.603878333333334,
  "time_utc": "2026-07-14T02:31:57+00:00",
  "text": "ECOGEMINI (tanker) is moored at 3 km off Piraeus. Reported destination: GRPIR."
 },
 {
  "id": "status-244690035",
  "type": "vessel_status",
  "mmsi": 244690035,
  "name": "BONTEKONING",
  "lat": 37.91408,
  "lon": 23.703773333333334,
  "time_utc": "2026-07-14T02:31:57+00:00",
  "text": "BONTEKONING (sailing) is stationary at 7 km off Piraeus. Reported destination: ATHENE."
 },
 {
  "id": "status-247360850",
  "type": "vessel_status",
  "mmsi": 247360850,
  "name": "STATHNIC IV",
  "lat": 37.93658833333333,
  "lon": 23.68653833333333,
  "time_utc": "2026-07-14T02:31:57+00:00",
  "text": "STATHNIC IV is stationary at 4 km off Piraeus."
 },
 {
  "id": "status-428711000",
  "type": "vessel_status",
  "mmsi": 428711000,
  "name": "THE ANGELS",
  "lat": 37.74337166666667,
  "lon": 23.427556666666664,
  "time_utc": "2026-07-14T02:31:57+00:00",
  "text": "THE ANGELS (sailing) is stationary at Aegina."
 },
 {
  "id": "status-518999866",
  "type": "vessel_status",
  "mmsi": 518999866,
  "name": "OCEAN DREAMWALER III",
  "lat": 37.80732833333333,
  "lon": 23.759658333333334,
  "time_utc": "2026-07-14T02:31:57+00:00",
  "text": "OCEAN DREAMWALER III (pleasure) is moored at open water (37.807, 23.760). Reported destination: GRATH."
 },
 {
  "id": "status-636021018",
  "type": "vessel_status",
  "mmsi": 636021018,
  "name": "DAWN",
  "lat": 37.96096166666667,
  "lon": 23.56165,
  "time_utc": "2026-07-14T02:31:57+00:00",
  "text": "DAWN (cargo) is moored at Perama. Reported destination: PIRAEUS."
 },
 {
  "id": "status-237732700",
  "type": "vessel_status",
  "mmsi": 237732700,
  "name": "IRENE'S",
  "lat": 37.93,
  "lon": 23.685103333333334,
  "time_utc": "2026-07-14T02:31:57+00:00",
  "text": "IRENE'S (pleasure) is moored at 5 km off Piraeus. Reported destination: CYCLADES."
 },
 {
  "id": "status-240496900",
  "type": "vessel_status",
  "mmsi": 240496900,
  "name": "LION FISH",
  "lat": 37.931711666666665,
  "lon": 23.684621666666665,
  "time_utc": "2026-07-14T02:31:57+00:00",
  "text": "LION FISH is stationary at 4 km off Piraeus."
 },
 {
  "id": "status-241596000",
  "type": "vessel_status",
  "mmsi": 241596000,
  "name": "AEGIS II",
  "lat": 37.95831333333333,
  "lon": 23.61279,
  "time_utc": "2026-07-14T02:31:57+00:00",
  "text": "AEGIS II (special craft) is moored at 3 km off Piraeus. Reported destination: KERATSINI."
 },
 {
  "id": "status-248771000",
  "type": "vessel_status",
  "mmsi": 248771000,
  "name": "MY FAN TOO",
  "lat": 37.92917333333333,
  "lon": 23.682753333333334,
  "time_utc": "2026-07-14T02:31:57+00:00",
  "text": "MY FAN TOO (pleasure) is stationary at 4 km off Piraeus. Reported destination: FLOISVOS."
 },
 {
  "id": "status-256837000",
  "type": "vessel_status",
  "mmsi": 256837000,
  "name": "SAN BIAGIO",
  "lat": 38.028636666666664,
  "lon": 23.59522666666667,
  "time_utc": "2026-07-14T02:31:57+00:00",
  "text": "SAN BIAGIO (tanker) is moored at 5 km off Elefsina. Reported destination: ELEUSUS."
 },
 {
  "id": "status-212681000",
  "type": "vessel_status",
  "mmsi": 212681000,
  "name": "POWER JET",
  "lat": 37.94956333333334,
  "lon": 23.601121666666664,
  "time_utc": "2026-07-14T02:31:57+00:00",
  "text": "POWER JET (high-speed craft) is moored at 3 km off Piraeus. Reported destination: DOKIMASTIKO."
 },
 {
  "id": "status-229153000",
  "type": "vessel_status",
  "mmsi": 229153000,
  "name": "BILMAR",
  "lat": 37.91385666666667,
  "lon": 23.703886666666666,
  "time_utc": "2026-07-14T02:31:57+00:00",
  "text": "BILMAR is moored at 7 km off Piraeus."
 },
 {
  "id": "status-232049041",
  "type": "vessel_status",
  "mmsi": 232049041,
  "name": "OMNIA",
  "lat": 37.93939833333333,
  "lon": 23.669508333333333,
  "time_utc": "2026-07-14T02:31:57+00:00",
  "text": "OMNIA is stationary at 3 km off Piraeus."
 },
 {
  "id": "status-237955000",
  "type": "vessel_status",
  "mmsi": 237955000,
  "name": "FAST FERRIES ANDROS",
  "lat": 38.042543333333334,
  "lon": 24.031698333333335,
  "time_utc": "2026-07-14T02:31:57+00:00",
  "text": "FAST FERRIES ANDROS (passenger) is at anchor at 3 km off Rafina. Reported destination: P M T A R."
 },
 {
  "id": "status-241871000",
  "type": "vessel_status",
  "mmsi": 241871000,
  "name": "ANASTASIA K II",
  "lat": 37.96066666666666,
  "lon": 23.5714,
  "time_utc": "2026-07-14T02:31:57+00:00",
  "text": "ANASTASIA K II (cargo) is moored at Perama. Reported destination: PERAMA."
 },
 {
  "id": "status-305058300",
  "type": "vessel_status",
  "mmsi": 305058300,
  "name": "ACERS",
  "lat": 38.03131166666667,
  "lon": 23.497458333333334,
  "time_utc": "2026-07-14T02:31:57+00:00",
  "text": "ACERS (tanker) is stationary at Elefsis Bay anchorage. Reported destination: GRPIR."
 },
 {
  "id": "status-538007240",
  "type": "vessel_status",
  "mmsi": 538007240,
  "name": "CHIOS SUNRISE",
  "lat": 38.04193166666666,
  "lon": 23.52958,
  "time_utc": "2026-07-14T02:31:57+00:00",
  "text": "CHIOS SUNRISE (cargo) is moored at Elefsina. Reported destination: GR ELE."
 },
 {
  "id": "status-240099800",
  "type": "vessel_status",
  "mmsi": 240099800,
  "name": "OCEAN SONG",
  "lat": 37.912074999999994,
  "lon": 23.70574,
  "time_utc": "2026-07-14T02:31:57+00:00",
  "text": "OCEAN SONG (sailing) is at anchor at 7 km off Piraeus."
 },
 {
  "id": "status-255902680",
  "type": "vessel_status",
  "mmsi": 255902680,
  "name": "LADY MALAK",
  "lat": 37.93859,
  "lon": 23.64877166666667,
  "time_utc": "2026-07-14T02:31:57+00:00",
  "text": "LADY MALAK (pleasure) is moored at Piraeus. Reported destination: ZEA MARINA."
 },
 {
  "id": "status-319268600",
  "type": "vessel_status",
  "mmsi": 319268600,
  "name": "RENAISSANCE",
  "lat": 37.79170666666666,
  "lon": 23.78312833333333,
  "time_utc": "2026-07-14T02:31:57+00:00",
  "text": "RENAISSANCE is at anchor at open water (37.792, 23.783). Reported destination: ASTIR."
 },
 {
  "id": "status-538010119",
  "type": "vessel_status",
  "mmsi": 538010119,
  "name": "LEONIDAS Z",
  "lat": 37.95457,
  "lon": 23.59526,
  "time_utc": "2026-07-14T02:31:57+00:00",
  "text": "LEONIDAS Z (cargo) is moored at 3 km off Perama. Reported destination: GRPIR."
 },
 {
  "id": "status-255912790",
  "type": "vessel_status",
  "mmsi": 255912790,
  "name": "BAGHEERA",
  "lat": 37.93215,
  "lon": 23.682556666666667,
  "time_utc": "2026-07-14T02:31:57+00:00",
  "text": "BAGHEERA is stationary at 4 km off Piraeus."
 },
 {
  "id": "status-367667210",
  "type": "vessel_status",
  "mmsi": 367667210,
  "name": "BAMBA",
  "lat": 37.99930666666667,
  "lon": 23.420036666666665,
  "time_utc": "2026-07-14T02:31:57+00:00",
  "text": "BAMBA (sailing) is stationary at open water (37.999, 23.420)."
 },
 {
  "id": "status-636022080",
  "type": "vessel_status",
  "mmsi": 636022080,
  "name": "MAZU",
  "lat": 37.85895666666667,
  "lon": 23.420268333333336,
  "time_utc": "2026-07-14T02:31:57+00:00",
  "text": "MAZU is underway at 9 knots near open water (37.859, 23.420), heading southeast."
 },
 {
  "id": "status-232060738",
  "type": "vessel_status",
  "mmsi": 232060738,
  "name": "PLAYMAKER",
  "lat": 37.914985,
  "lon": 23.701278333333335,
  "time_utc": "2026-07-14T02:31:57+00:00",
  "text": "PLAYMAKER is stationary at 6 km off Piraeus."
 },
 {
  "id": "status-241793000",
  "type": "vessel_status",
  "mmsi": 241793000,
  "name": "L' EQUINOX",
  "lat": 37.735969999999995,
  "lon": 23.423561666666668,
  "time_utc": "2026-07-14T02:31:57+00:00",
  "text": "L' EQUINOX (pleasure) is stationary at Aegina."
 },
 {
  "id": "status-240247200",
  "type": "vessel_status",
  "mmsi": 240247200,
  "name": "NIMBUS",
  "lat": 37.91272333333333,
  "lon": 23.701900000000002,
  "time_utc": "2026-07-14T02:31:57+00:00",
  "text": "NIMBUS (sailing) is stationary at 7 km off Piraeus."
 },
 {
  "id": "status-240650900",
  "type": "vessel_status",
  "mmsi": 240650900,
  "name": "ONAR",
  "lat": 37.35097833333334,
  "lon": 23.46609,
  "time_utc": "2026-07-14T02:31:57+00:00",
  "text": "ONAR is stationary at Hydra."
 },
 {
  "id": "status-248198000",
  "type": "vessel_status",
  "mmsi": 248198000,
  "name": "EMOTION2",
  "lat": 37.93278166666666,
  "lon": 23.647663333333334,
  "time_utc": "2026-07-14T02:31:57+00:00",
  "text": "EMOTION2 (pleasure) is moored at Piraeus. Reported destination: ZEA."
 },
 {
  "id": "status-256002670",
  "type": "vessel_status",
  "mmsi": 256002670,
  "name": "TIARE'",
  "lat": 37.939745,
  "lon": 23.669143333333334,
  "time_utc": "2026-07-14T02:31:57+00:00",
  "text": "TIARE' (sailing) is stationary at 3 km off Piraeus."
 },
 {
  "id": "status-319431000",
  "type": "vessel_status",
  "mmsi": 319431000,
  "name": "HALCYON",
  "lat": 37.93032,
  "lon": 23.684266666666666,
  "time_utc": "2026-07-14T02:31:57+00:00",
  "text": "HALCYON (pleasure) is moored at 4 km off Piraeus."
 },
 {
  "id": "status-375025000",
  "type": "vessel_status",
  "mmsi": 375025000,
  "name": "HALLO",
  "lat": 37.96103666666667,
  "lon": 23.564633333333333,
  "time_utc": "2026-07-14T02:31:57+00:00",
  "text": "HALLO (pleasure) is moored at Perama. Reported destination: SEA TRIAL."
 },
 {
  "id": "status-239923000",
  "type": "vessel_status",
  "mmsi": 239923000,
  "name": "BLUE STAR NAXOS",
  "lat": 37.94789333333333,
  "lon": 23.639388333333333,
  "time_utc": "2026-07-14T02:31:57+00:00",
  "text": "BLUE STAR NAXOS (passenger) is moored at Piraeus. Reported destination: A A D N P P."
 },
 {
  "id": "status-240685000",
  "type": "vessel_status",
  "mmsi": 240685000,
  "name": "ELYROS",
  "lat": 37.603905000000005,
  "lon": 23.795168333333333,
  "time_utc": "2026-07-14T02:31:57+00:00",
  "text": "ELYROS (passenger) is underway at 21 knots near open water (37.604, 23.795), heading northwest. Reported destination: SOUDA."
 },
 {
  "id": "status-241621000",
  "type": "vessel_status",
  "mmsi": 241621000,
  "name": "CHRISTOS XLII",
  "lat": 37.95679,
  "lon": 23.606015,
  "time_utc": "2026-07-14T02:31:57+00:00",
  "text": "CHRISTOS XLII (special craft) is stationary at 3 km off Piraeus. Reported destination: GR PIR."
 },
 {
  "id": "status-239808200",
  "type": "vessel_status",
  "mmsi": 239808200,
  "name": "LEON",
  "lat": 37.95663833333333,
  "lon": 23.605286666666665,
  "time_utc": "2026-07-14T02:31:57+00:00",
  "text": "LEON (special craft) is stationary at 3 km off Piraeus."
 },
 {
  "id": "status-241583000",
  "type": "vessel_status",
  "mmsi": 241583000,
  "name": "VERNICOS LIBERTY",
  "lat": 37.95721833333334,
  "lon": 23.609238333333334,
  "time_utc": "2026-07-14T02:31:57+00:00",
  "text": "VERNICOS LIBERTY (special craft) is stationary at 3 km off Piraeus. Reported destination: PIRAEUS."
 },
 {
  "id": "status-241792000",
  "type": "vessel_status",
  "mmsi": 241792000,
  "name": "VERNICOS SCAFI II",
  "lat": 37.95763,
  "lon": 23.6098,
  "time_utc": "2026-07-14T02:31:57+00:00",
  "text": "VERNICOS SCAFI II (special craft) is stationary at 3 km off Piraeus. Reported destination: PIRAEUS."
 },
 {
  "id": "status-248175000",
  "type": "vessel_status",
  "mmsi": 248175000,
  "name": "ARESYA",
  "lat": 37.93904833333333,
  "lon": 23.669021666666666,
  "time_utc": "2026-07-14T02:31:57+00:00",
  "text": "ARESYA (pleasure) is stationary at 3 km off Piraeus."
 },
 {
  "id": "status-237448400",
  "type": "vessel_status",
  "mmsi": 237448400,
  "name": "KATERINA STAR",
  "lat": 37.260668333333335,
  "lon": 23.16546333333333,
  "time_utc": "2026-07-14T02:31:57+00:00",
  "text": "KATERINA STAR (passenger) is stationary at Spetses. Reported destination: SPETSES-KOSTA-SP/SES."
 },
 {
  "id": "status-240317000",
  "type": "vessel_status",
  "mmsi": 240317000,
  "name": "SUPERSPEED JET 4",
  "lat": 37.94525,
  "lon": 23.639533333333336,
  "time_utc": "2026-07-14T02:31:57+00:00",
  "text": "SUPERSPEED JET 4 is moored at Piraeus."
 },
 {
  "id": "status-241013000",
  "type": "vessel_status",
  "mmsi": 241013000,
  "name": "SEAVEN OCEAN",
  "lat": 38.019915,
  "lon": 23.513008333333335,
  "time_utc": "2026-07-14T02:31:57+00:00",
  "text": "SEAVEN OCEAN (tanker) is at anchor at Elefsis Bay anchorage. Reported destination: GR KGS."
 },
 {
  "id": "status-241435000",
  "type": "vessel_status",
  "mmsi": 241435000,
  "name": "SUPERFERRY",
  "lat": 38.05356166666666,
  "lon": 24.01473,
  "time_utc": "2026-07-14T02:31:57+00:00",
  "text": "SUPERFERRY (passenger) is at anchor at 3 km off Rafina. Reported destination: R-T-M-N-P-R."
 },
 {
  "id": "status-249965000",
  "type": "vessel_status",
  "mmsi": 249965000,
  "name": "MADIZ",
  "lat": 37.960175,
  "lon": 23.5711,
  "time_utc": "2026-07-14T02:31:57+00:00",
  "text": "MADIZ (pleasure) is moored at Perama. Reported destination: PERAMA."
 },
 {
  "id": "status-240205400",
  "type": "vessel_status",
  "mmsi": 240205400,
  "name": "KALLIOPI G",
  "lat": 37.95856166666667,
  "lon": 23.610996666666665,
  "time_utc": "2026-07-14T02:31:57+00:00",
  "text": "KALLIOPI G (tanker) is stationary at 3 km off Piraeus. Reported destination: PIRAEUS."
 },
 {
  "id": "status-240585500",
  "type": "vessel_status",
  "mmsi": 240585500,
  "name": "LADY MARY",
  "lat": 37.262445,
  "lon": 23.163096666666668,
  "time_utc": "2026-07-14T02:31:57+00:00",
  "text": "LADY MARY is stationary at Spetses."
 },
 {
  "id": "status-241006000",
  "type": "vessel_status",
  "mmsi": 241006000,
  "name": "ELIN POSEIDON",
  "lat": 38.01556166666667,
  "lon": 23.53736,
  "time_utc": "2026-07-14T02:31:57+00:00",
  "text": "ELIN POSEIDON (tanker) is at anchor at 2 km off Elefsina. Reported destination: GRASS."
 },
 {
  "id": "status-241678000",
  "type": "vessel_status",
  "mmsi": 241678000,
  "name": "HIGHSPEED 3",
  "lat": 37.94490666666666,
  "lon": 23.638188333333336,
  "time_utc": "2026-07-14T02:31:57+00:00",
  "text": "HIGHSPEED 3 is moored at Piraeus."
 },
 {
  "id": "status-241893000",
  "type": "vessel_status",
  "mmsi": 241893000,
  "name": "AGIOS ANTONIOS",
  "lat": 38.031616666666665,
  "lon": 23.54145,
  "time_utc": "2026-07-14T02:31:57+00:00",
  "text": "AGIOS ANTONIOS (cargo) is moored at Elefsina. Reported destination: GREEU."
 },
 {
  "id": "status-232066978",
  "type": "vessel_status",
  "mmsi": 232066978,
  "name": "TASOS",
  "lat": 37.875295,
  "lon": 23.728,
  "time_utc": "2026-07-14T02:31:57+00:00",
  "text": "TASOS (pleasure) is stationary at open water (37.875, 23.728)."
 },
 {
  "id": "status-240541200",
  "type": "vessel_status",
  "mmsi": 240541200,
  "name": "EFKRATI",
  "lat": 37.262638333333335,
  "lon": 23.162656666666667,
  "time_utc": "2026-07-14T02:31:57+00:00",
  "text": "EFKRATI is stationary at Spetses."
 },
 {
  "id": "status-241416000",
  "type": "vessel_status",
  "mmsi": 241416000,
  "name": "MARLA",
  "lat": 37.93205,
  "lon": 23.650858333333336,
  "time_utc": "2026-07-14T02:31:57+00:00",
  "text": "MARLA (pleasure) is moored at Piraeus. Reported destination: PIRAEUS."
 },
 {
  "id": "status-339306000",
  "type": "vessel_status",
  "mmsi": 339306000,
  "name": "MARIA",
  "lat": 37.930854999999994,
  "lon": 23.68315,
  "time_utc": "2026-07-14T02:31:57+00:00",
  "text": "MARIA is stationary at 4 km off Piraeus. Reported destination: FLISVOS."
 },
 {
  "id": "status-538010878",
  "type": "vessel_status",
  "mmsi": 538010878,
  "name": "ASPHALT SONATA",
  "lat": 37.609805,
  "lon": 23.719656666666666,
  "time_utc": "2026-07-14T02:31:57+00:00",
  "text": "ASPHALT SONATA is underway at 13 knots near open water (37.610, 23.720), heading south."
 },
 {
  "id": "status-240081400",
  "type": "vessel_status",
  "mmsi": 240081400,
  "name": "ZEN",
  "lat": 37.269795,
  "lon": 23.154428333333332,
  "time_utc": "2026-07-14T02:31:57+00:00",
  "text": "ZEN (pleasure) is stationary at Spetses. Reported destination: SARONIKOS."
 },
 {
  "id": "status-241811000",
  "type": "vessel_status",
  "mmsi": 241811000,
  "name": "WHITE PEARL I",
  "lat": 37.91100166666667,
  "lon": 23.704155,
  "time_utc": "2026-07-14T02:31:57+00:00",
  "text": "WHITE PEARL I is at anchor at 7 km off Piraeus. Reported destination: ALIMOS."
 },
 {
  "id": "status-211166830",
  "type": "vessel_status",
  "mmsi": 211166830,
  "name": "SARAVA II",
  "lat": 37.35117,
  "lon": 23.465410000000002,
  "time_utc": "2026-07-14T02:31:57+00:00",
  "text": "SARAVA II (pleasure) is stationary at Hydra."
 },
 {
  "id": "status-239361800",
  "type": "vessel_status",
  "mmsi": 239361800,
  "name": "ARCELIA",
  "lat": 37.875728333333335,
  "lon": 23.726668333333336,
  "time_utc": "2026-07-14T02:31:57+00:00",
  "text": "ARCELIA (pleasure) is moored at open water (37.876, 23.727). Reported destination: ELEFSINA."
 },
 {
  "id": "status-239978100",
  "type": "vessel_status",
  "mmsi": 239978100,
  "name": "BLUE DREAM",
  "lat": 37.936490000000006,
  "lon": 23.661668333333335,
  "time_utc": "2026-07-14T02:31:57+00:00",
  "text": "BLUE DREAM (pleasure) is stationary at 2 km off Piraeus."
 },
 {
  "id": "status-210799000",
  "type": "vessel_status",
  "mmsi": 210799000,
  "name": "ANNITA M",
  "lat": 37.35115,
  "lon": 23.46517833333333,
  "time_utc": "2026-07-14T02:31:57+00:00",
  "text": "ANNITA M is stationary at Hydra."
 },
 {
  "id": "status-538005401",
  "type": "vessel_status",
  "mmsi": 538005401,
  "name": "STI HACKNEY",
  "lat": 38.002426666666665,
  "lon": 23.527101666666667,
  "time_utc": "2026-07-14T02:31:57+00:00",
  "text": "STI HACKNEY (tanker) is at anchor at 4 km off Elefsina. Reported destination: HRPLE>>GRFLS."
 },
 {
  "id": "status-241756000",
  "type": "vessel_status",
  "mmsi": 241756000,
  "name": "KIMATA",
  "lat": 37.26228666666667,
  "lon": 23.165615,
  "time_utc": "2026-07-14T02:31:57+00:00",
  "text": "KIMATA (sailing) is at anchor at Spetses."
 },
 {
  "id": "status-240743000",
  "type": "vessel_status",
  "mmsi": 240743000,
  "name": "SEAVEN PROGRESS",
  "lat": 37.947334999999995,
  "lon": 23.613228333333332,
  "time_utc": "2026-07-14T02:31:57+00:00",
  "text": "SEAVEN PROGRESS (cargo) is moored at 2 km off Piraeus. Reported destination: GR PIR."
 },
 {
  "id": "status-518516000",
  "type": "vessel_status",
  "mmsi": 518516000,
  "name": "FORTY LOVE",
  "lat": 37.85847666666667,
  "lon": 23.74188666666667,
  "time_utc": "2026-07-14T02:31:57+00:00",
  "text": "FORTY LOVE is at anchor at open water (37.858, 23.742)."
 },
 {
  "id": "status-240407900",
  "type": "vessel_status",
  "mmsi": 240407900,
  "name": "ALEXANDRA  II",
  "lat": 37.94153666666667,
  "lon": 23.670858333333335,
  "time_utc": "2026-07-14T02:31:57+00:00",
  "text": "ALEXANDRA  II (pleasure) is stationary at 3 km off Piraeus."
 },
 {
  "id": "status-240664200",
  "type": "vessel_status",
  "mmsi": 240664200,
  "name": "DESTINY",
  "lat": 37.261448333333334,
  "lon": 23.164095,
  "time_utc": "2026-07-14T02:31:57+00:00",
  "text": "DESTINY is stationary at Spetses."
 },
 {
  "id": "status-237932700",
  "type": "vessel_status",
  "mmsi": 237932700,
  "name": "ATHINA P",
  "lat": 37.963475,
  "lon": 23.528705,
  "time_utc": "2026-07-14T02:31:57+00:00",
  "text": "ATHINA P (passenger) is underway at 5 knots near Salamina (Paloukia), heading west. Reported destination: PALOUKIA-PERAMA."
 },
 {
  "id": "status-261009057",
  "type": "vessel_status",
  "mmsi": 261009057,
  "name": "ANDIAMO",
  "lat": 37.741976666666666,
  "lon": 23.427466666666664,
  "time_utc": "2026-07-14T02:31:57+00:00",
  "text": "ANDIAMO is stationary at Aegina."
 },
 {
  "id": "status-376514000",
  "type": "vessel_status",
  "mmsi": 376514000,
  "name": "PROTUG 42",
  "lat": 37.95145333333333,
  "lon": 23.548408333333334,
  "time_utc": "2026-07-14T02:31:57+00:00",
  "text": "PROTUG 42 is moored at 2 km off Salamina (Paloukia)."
 },
 {
  "id": "status-244928000",
  "type": "vessel_status",
  "mmsi": 244928000,
  "name": "VERTOM CYTA",
  "lat": 38.03543666666667,
  "lon": 23.538733333333333,
  "time_utc": "2026-07-14T02:31:57+00:00",
  "text": "VERTOM CYTA (cargo) is moored at Elefsina. Reported destination: GRELE."
 },
 {
  "id": "status-215285000",
  "type": "vessel_status",
  "mmsi": 215285000,
  "name": "M/Y RARE FIND",
  "lat": 37.930730000000004,
  "lon": 23.68341666666667,
  "time_utc": "2026-07-14T02:31:57+00:00",
  "text": "M/Y RARE FIND (pleasure) is stationary at 4 km off Piraeus. Reported destination: FLOISVOS."
 },
 {
  "id": "status-244850851",
  "type": "vessel_status",
  "mmsi": 244850851,
  "name": "SIDARTA",
  "lat": 37.248655,
  "lon": 23.16697,
  "time_utc": "2026-07-14T02:31:57+00:00",
  "text": "SIDARTA is stationary at 2 km off Spetses."
 },
 {
  "id": "status-319257400",
  "type": "vessel_status",
  "mmsi": 319257400,
  "name": "JUNELUCK",
  "lat": 37.92921333333334,
  "lon": 23.68291333333333,
  "time_utc": "2026-07-14T02:31:57+00:00",
  "text": "JUNELUCK (pleasure) is moored at 4 km off Piraeus. Reported destination: FLISVOS."
 },
 {
  "id": "status-636022888",
  "type": "vessel_status",
  "mmsi": 636022888,
  "name": "ATLAS STAR",
  "lat": 37.900306666666665,
  "lon": 23.083681666666667,
  "time_utc": "2026-07-14T02:31:57+00:00",
  "text": "ATLAS STAR (tanker) is at anchor at 7 km off Corinth Canal (Isthmia). Reported destination: AGIOI THEODOROI."
 },
 {
  "id": "status-241726000",
  "type": "vessel_status",
  "mmsi": 241726000,
  "name": "KNOSSOS PALACE",
  "lat": 37.705974999999995,
  "lon": 23.747558333333334,
  "time_utc": "2026-07-14T02:31:57+00:00",
  "text": "KNOSSOS PALACE (passenger) is underway at 20 knots near open water (37.706, 23.748), heading north. Reported destination: GRPIR."
 },
 {
  "id": "status-241917000",
  "type": "vessel_status",
  "mmsi": 241917000,
  "name": "BENIK",
  "lat": 37.26175,
  "lon": 23.164733333333334,
  "time_utc": "2026-07-14T02:31:57+00:00",
  "text": "BENIK (pleasure) is stationary at Spetses. Reported destination: AEGEAN SEA."
 },
 {
  "id": "status-256001849",
  "type": "vessel_status",
  "mmsi": 256001849,
  "name": "LYDIA S",
  "lat": 37.941678333333336,
  "lon": 23.67040666666667,
  "time_utc": "2026-07-14T02:31:57+00:00",
  "text": "LYDIA S is stationary at 3 km off Piraeus."
 },
 {
  "id": "status-636092914",
  "type": "vessel_status",
  "mmsi": 636092914,
  "name": "UAFL RACER",
  "lat": 37.84477166666667,
  "lon": 23.639178333333334,
  "time_utc": "2026-07-14T02:31:57+00:00",
  "text": "UAFL RACER (cargo) is underway at 6 knots near open water (37.845, 23.639), heading northwest. Reported destination: GRPIR."
 },
 {
  "id": "status-240780000",
  "type": "vessel_status",
  "mmsi": 240780000,
  "name": "FELIGO V",
  "lat": 37.94166499999999,
  "lon": 23.670073333333335,
  "time_utc": "2026-07-14T02:31:57+00:00",
  "text": "FELIGO V (pleasure) is moored at 3 km off Piraeus. Reported destination: MARINA ATHINON."
 },
 {
  "id": "status-241955000",
  "type": "vessel_status",
  "mmsi": 241955000,
  "name": "NINO",
  "lat": 37.931940000000004,
  "lon": 23.680056666666665,
  "time_utc": "2026-07-14T02:31:57+00:00",
  "text": "NINO (pleasure) is moored at 4 km off Piraeus. Reported destination: PORTOHELI."
 },
 {
  "id": "status-256005279",
  "type": "vessel_status",
  "mmsi": 256005279,
  "name": "ARIA",
  "lat": 37.93057833333333,
  "lon": 23.68507,
  "time_utc": "2026-07-14T02:31:57+00:00",
  "text": "ARIA is stationary at 4 km off Piraeus."
 },
 {
  "id": "status-249853000",
  "type": "vessel_status",
  "mmsi": 249853000,
  "name": "WOMBAT",
  "lat": 37.932766666666666,
  "lon": 23.68228,
  "time_utc": "2026-07-14T02:31:57+00:00",
  "text": "WOMBAT (pleasure) is moored at 4 km off Piraeus."
 },
 {
  "id": "status-319212600",
  "type": "vessel_status",
  "mmsi": 319212600,
  "name": "ALEX",
  "lat": 37.93180333333333,
  "lon": 23.680023333333335,
  "time_utc": "2026-07-14T02:31:57+00:00",
  "text": "ALEX (pleasure) is moored at 4 km off Piraeus. Reported destination: ATHENS / FLISVOS."
 },
 {
  "id": "status-229739000",
  "type": "vessel_status",
  "mmsi": 229739000,
  "name": "NATALIA V",
  "lat": 37.292923333333334,
  "lon": 23.160283333333332,
  "time_utc": "2026-07-14T02:31:57+00:00",
  "text": "NATALIA V (pleasure) is stationary at 3 km off Spetses. Reported destination: SARONIC."
 },
 {
  "id": "status-341572001",
  "type": "vessel_status",
  "mmsi": 341572001,
  "name": "LEONIDAS",
  "lat": 37.935925,
  "lon": 23.670301666666667,
  "time_utc": "2026-07-14T02:31:57+00:00",
  "text": "LEONIDAS is stationary at 3 km off Piraeus."
 },
 {
  "id": "status-240396300",
  "type": "vessel_status",
  "mmsi": 240396300,
  "name": "ELEMENT",
  "lat": 37.913893333333334,
  "lon": 23.704191666666667,
  "time_utc": "2026-07-14T02:31:57+00:00",
  "text": "ELEMENT is moored at 7 km off Piraeus."
 },
 {
  "id": "status-249867000",
  "type": "vessel_status",
  "mmsi": 249867000,
  "name": "BLADE6",
  "lat": 37.94161166666667,
  "lon": 23.669026666666664,
  "time_utc": "2026-07-14T02:31:57+00:00",
  "text": "BLADE6 (pleasure) is stationary at 3 km off Piraeus. Reported destination: ATHENS MARINA."
 },
 {
  "id": "status-249902000",
  "type": "vessel_status",
  "mmsi": 249902000,
  "name": "BLUE SYMPHONIE",
  "lat": 37.96006833333333,
  "lon": 23.576913333333334,
  "time_utc": "2026-07-14T02:31:57+00:00",
  "text": "BLUE SYMPHONIE (pleasure) is stationary at 1 km off Perama. Reported destination: AGISTRI."
 },
 {
  "id": "status-240544900",
  "type": "vessel_status",
  "mmsi": 240544900,
  "name": "ATALANTI",
  "lat": 37.93938166666667,
  "lon": 23.669413333333335,
  "time_utc": "2026-07-14T02:31:57+00:00",
  "text": "ATALANTI (pleasure) is moored at 3 km off Piraeus. Reported destination: PIRAEUS."
 },
 {
  "id": "status-636013899",
  "type": "vessel_status",
  "mmsi": 636013899,
  "name": "BACCARA",
  "lat": 37.932045,
  "lon": 23.684601666666666,
  "time_utc": "2026-07-14T02:31:57+00:00",
  "text": "BACCARA is stationary at 4 km off Piraeus."
 },
 {
  "id": "status-237478500",
  "type": "vessel_status",
  "mmsi": 237478500,
  "name": "TOULA MARIA",
  "lat": 37.99993666666667,
  "lon": 23.421375,
  "time_utc": "2026-07-14T02:31:57+00:00",
  "text": "TOULA MARIA is stationary at open water (38.000, 23.421)."
 },
 {
  "id": "status-240136100",
  "type": "vessel_status",
  "mmsi": 240136100,
  "name": "INVADER",
  "lat": 37.93213333333333,
  "lon": 23.65148333333333,
  "time_utc": "2026-07-14T02:31:57+00:00",
  "text": "INVADER (pleasure) is at anchor at Piraeus. Reported destination: SARONIC."
 },
 {
  "id": "status-239028000",
  "type": "vessel_status",
  "mmsi": 239028000,
  "name": "HLIAS MIGGOS",
  "lat": 38.02479,
  "lon": 24.010436666666667,
  "time_utc": "2026-07-14T02:31:57+00:00",
  "text": "HLIAS MIGGOS (fishing) is stationary at Rafina."
 },
 {
  "id": "status-240293500",
  "type": "vessel_status",
  "mmsi": 240293500,
  "name": "CHRISTOS XLVII",
  "lat": 37.961059999999996,
  "lon": 23.555515,
  "time_utc": "2026-07-14T02:31:57+00:00",
  "text": "CHRISTOS XLVII is stationary at 1 km off Perama."
 },
 {
  "id": "status-237112600",
  "type": "vessel_status",
  "mmsi": 237112600,
  "name": "AG.ANTONIOS",
  "lat": 38.035963333333335,
  "lon": 23.551925,
  "time_utc": "2026-07-14T02:31:57+00:00",
  "text": "AG.ANTONIOS (cargo) is moored at Elefsina. Reported destination: GREEU."
 },
 {
  "id": "status-240031600",
  "type": "vessel_status",
  "mmsi": 240031600,
  "name": "PROTOPOROS X",
  "lat": 37.96033666666666,
  "lon": 23.534843333333335,
  "time_utc": "2026-07-14T02:31:57+00:00",
  "text": "PROTOPOROS X (passenger) is underway at 7 knots near Salamina (Paloukia), heading southeast. Reported destination: PALOUKIA-PERAMA."
 },
 {
  "id": "status-240484000",
  "type": "vessel_status",
  "mmsi": 240484000,
  "name": "EYAGGELISTRIA<<",
  "lat": 37.9576,
  "lon": 23.535091666666666,
  "time_utc": "2026-07-14T02:31:57+00:00",
  "text": "EYAGGELISTRIA<< is stationary at 1 km off Salamina (Paloukia)."
 },
 {
  "id": "status-271040008",
  "type": "vessel_status",
  "mmsi": 271040008,
  "name": "BERNARD A",
  "lat": 37.55128333333334,
  "lon": 23.926355,
  "time_utc": "2026-07-14T02:31:57+00:00",
  "text": "BERNARD A (cargo) is underway at 1 knots near open water (37.551, 23.926), heading northwest. Reported destination: GRPIR."
 },
 {
  "id": "status-237573900",
  "type": "vessel_status",
  "mmsi": 237573900,
  "name": "CHRISTOS LIII",
  "lat": 37.934531666666665,
  "lon": 23.618321666666667,
  "time_utc": "2026-07-14T02:31:57+00:00",
  "text": "CHRISTOS LIII is stationary at Piraeus."
 },
 {
  "id": "status-240340900",
  "type": "vessel_status",
  "mmsi": 240340900,
  "name": "CHRISTOS XXVIII",
  "lat": 37.933501666666665,
  "lon": 23.62122833333333,
  "time_utc": "2026-07-14T02:31:57+00:00",
  "text": "CHRISTOS XXVIII is stationary at Piraeus."
 },
 {
  "id": "status-319108500",
  "type": "vessel_status",
  "mmsi": 319108500,
  "name": "LIQUID SKY",
  "lat": 37.931198333333334,
  "lon": 23.649471666666667,
  "time_utc": "2026-07-14T02:31:57+00:00",
  "text": "LIQUID SKY is stationary at Piraeus. Reported destination: ZEA MARINA."
 },
 {
  "id": "status-636022661",
  "type": "vessel_status",
  "mmsi": 636022661,
  "name": "MSC NICOLE X",
  "lat": 37.807085,
  "lon": 23.680086666666668,
  "time_utc": "2026-07-14T02:31:57+00:00",
  "text": "MSC NICOLE X (cargo) is underway at 3 knots near open water (37.807, 23.680), heading northwest. Reported destination: PIRAEUS (GRPIR)."
 },
 {
  "id": "status-249428000",
  "type": "vessel_status",
  "mmsi": 249428000,
  "name": "LARRIANE MAE",
  "lat": 37.81048666666666,
  "lon": 23.763963333333333,
  "time_utc": "2026-07-14T02:31:57+00:00",
  "text": "LARRIANE MAE is stationary at open water (37.810, 23.764)."
 },
 {
  "id": "status-215682000",
  "type": "vessel_status",
  "mmsi": 215682000,
  "name": "XASTERIA",
  "lat": 37.930475,
  "lon": 23.683736666666668,
  "time_utc": "2026-07-14T02:31:57+00:00",
  "text": "XASTERIA (sailing) is stationary at 4 km off Piraeus. Reported destination: FLISVOS."
 },
 {
  "id": "status-339000037",
  "type": "vessel_status",
  "mmsi": 339000037,
  "name": "INFINITY",
  "lat": 37.93134833333333,
  "lon": 23.649526666666667,
  "time_utc": "2026-07-14T02:31:57+00:00",
  "text": "INFINITY (pleasure) is stationary at Piraeus. Reported destination: ZEA."
 },
 {
  "id": "status-248034000",
  "type": "vessel_status",
  "mmsi": 248034000,
  "name": "GALA I",
  "lat": 37.269866666666665,
  "lon": 23.154495,
  "time_utc": "2026-07-14T02:31:57+00:00",
  "text": "GALA I is moored at Spetses."
 },
 {
  "id": "status-538072442",
  "type": "vessel_status",
  "mmsi": 538072442,
  "name": "MY DEMARCH",
  "lat": 37.26163833333333,
  "lon": 23.164923333333334,
  "time_utc": "2026-07-14T02:31:57+00:00",
  "text": "MY DEMARCH is stationary at Spetses."
 },
 {
  "id": "status-563154500",
  "type": "vessel_status",
  "mmsi": 563154500,
  "name": "MAERSK VALLETTA",
  "lat": 37.45890333333333,
  "lon": 23.79823,
  "time_utc": "2026-07-14T02:31:57+00:00",
  "text": "MAERSK VALLETTA (cargo) is stationary at open water (37.459, 23.798). Reported destination: EGPSD>>GRPIR."
 },
 {
  "id": "status-256002937",
  "type": "vessel_status",
  "mmsi": 256002937,
  "name": "TWO KAY",
  "lat": 37.351276666666664,
  "lon": 23.4653,
  "time_utc": "2026-07-14T02:31:57+00:00",
  "text": "TWO KAY is stationary at Hydra. Reported destination: HYDRA."
 },
 {
  "id": "status-503159190",
  "type": "vessel_status",
  "mmsi": 503159190,
  "name": "BREEZE",
  "lat": 37.338809999999995,
  "lon": 23.438151666666666,
  "time_utc": "2026-07-14T02:31:57+00:00",
  "text": "BREEZE is stationary at 3 km off Hydra."
 },
 {
  "id": "status-241485000",
  "type": "vessel_status",
  "mmsi": 241485000,
  "name": "PRUDENT WARRIOR",
  "lat": 37.89776833333334,
  "lon": 23.05723,
  "time_utc": "2026-07-14T02:31:57+00:00",
  "text": "PRUDENT WARRIOR (tanker) is at anchor at 5 km off Corinth Canal (Isthmia). Reported destination: GRAGT."
 },
 {
  "id": "status-241789000",
  "type": "vessel_status",
  "mmsi": 241789000,
  "name": "HAKUNA MATATA",
  "lat": 37.74580666666667,
  "lon": 23.42598333333333,
  "time_utc": "2026-07-14T02:31:57+00:00",
  "text": "HAKUNA MATATA (passenger) is stationary at Aegina."
 },
 {
  "id": "status-249091000",
  "type": "vessel_status",
  "mmsi": 249091000,
  "name": "KOGO",
  "lat": 37.69828333333333,
  "lon": 23.32116166666667,
  "time_utc": "2026-07-14T02:31:57+00:00",
  "text": "KOGO (pleasure) is at anchor at 3 km off Agistri (Skala). Reported destination: AGISTRI."
 },
 {
  "id": "status-237741100",
  "type": "vessel_status",
  "mmsi": 237741100,
  "name": "TAKA",
  "lat": 37.696661666666664,
  "lon": 23.32818166666667,
  "time_utc": "2026-07-14T02:31:57+00:00",
  "text": "TAKA is stationary at 3 km off Agistri (Skala)."
 },
 {
  "id": "status-239982500",
  "type": "vessel_status",
  "mmsi": 239982500,
  "name": "NOVA",
  "lat": 37.931066666666666,
  "lon": 23.648059999999997,
  "time_utc": "2026-07-14T02:31:57+00:00",
  "text": "NOVA is stationary at Piraeus."
 },
 {
  "id": "status-240150000",
  "type": "vessel_status",
  "mmsi": 240150000,
  "name": "AGIOS DIMITRIOS",
  "lat": 37.96245666666667,
  "lon": 23.57115,
  "time_utc": "2026-07-14T02:31:57+00:00",
  "text": "AGIOS DIMITRIOS is stationary at Perama."
 },
 {
  "id": "status-207842480",
  "type": "vessel_status",
  "mmsi": 207842480,
  "name": "VIVA 4",
  "lat": 37.280215,
  "lon": 23.186138333333336,
  "time_utc": "2026-07-14T02:31:57+00:00",
  "text": "VIVA 4 is underway at 7 knots near 3 km off Spetses, heading west."
 },
 {
  "id": "status-255915842",
  "type": "vessel_status",
  "mmsi": 255915842,
  "name": "NORDLUCHS",
  "lat": 37.57745166666667,
  "lon": 23.669518333333333,
  "time_utc": "2026-07-14T02:31:57+00:00",
  "text": "NORDLUCHS is stationary at open water (37.577, 23.670)."
 },
 {
  "id": "status-248549000",
  "type": "vessel_status",
  "mmsi": 248549000,
  "name": "NEPTUNE ILIAD",
  "lat": 37.87601666666667,
  "lon": 23.579795,
  "time_utc": "2026-07-14T02:31:57+00:00",
  "text": "NEPTUNE ILIAD is underway at 8 knots near Piraeus anchorage, heading northwest."
 },
 {
  "id": "status-304029000",
  "type": "vessel_status",
  "mmsi": 304029000,
  "name": "FINOLA M",
  "lat": 37.713605,
  "lon": 23.729435000000002,
  "time_utc": "2026-07-14T02:31:57+00:00",
  "text": "FINOLA M is underway at 6 knots near open water (37.714, 23.729), heading northwest."
 },
 {
  "id": "status-240870000",
  "type": "vessel_status",
  "mmsi": 240870000,
  "name": "AEGEAN TIFFANY",
  "lat": 37.932161666666666,
  "lon": 23.262546666666665,
  "time_utc": "2026-07-14T02:31:57+00:00",
  "text": "AEGEAN TIFFANY is underway at 8 knots near open water (37.932, 23.263), heading northeast."
 },
 {
  "id": "status-311316000",
  "type": "vessel_status",
  "mmsi": 311316000,
  "name": "EXPLORER OF THE SEAS",
  "lat": 37.79411666666667,
  "lon": 23.676471666666664,
  "time_utc": "2026-07-14T02:31:57+00:00",
  "text": "EXPLORER OF THE SEAS is underway at 19 knots near open water (37.794, 23.676), heading northwest."
 },
 {
  "id": "status-352002491",
  "type": "vessel_status",
  "mmsi": 352002491,
  "name": "MARILOU",
  "lat": 37.754580000000004,
  "lon": 23.712988333333332,
  "time_utc": "2026-07-14T02:31:57+00:00",
  "text": "MARILOU is underway at 6 knots near open water (37.755, 23.713), heading northwest."
 },
 {
  "id": "status-240763900",
  "type": "vessel_status",
  "mmsi": 240763900,
  "name": "",
  "lat": 37.260753333333334,
  "lon": 23.254921666666668,
  "time_utc": "2026-07-14T02:31:57+00:00",
  "text": "MMSI 240763900 is underway at 8 knots near open water (37.261, 23.255), heading west."
 },
 {
  "id": "status-248223000",
  "type": "vessel_status",
  "mmsi": 248223000,
  "name": "HOW MUCH IS ENOUGH",
  "lat": 37.23092,
  "lon": 23.556236666666667,
  "time_utc": "2026-07-14T02:31:57+00:00",
  "text": "HOW MUCH IS ENOUGH is underway at 14 knots near open water (37.231, 23.556), heading west."
 },
 {
  "id": "status-248704000",
  "type": "vessel_status",
  "mmsi": 248704000,
  "name": "OPTASIA",
  "lat": 37.19624666666667,
  "lon": 23.358636666666666,
  "time_utc": "2026-07-14T02:31:57+00:00",
  "text": "OPTASIA is underway at 12 knots near open water (37.196, 23.359), heading northwest."
 },
 {
  "id": "status-256378000",
  "type": "vessel_status",
  "mmsi": 256378000,
  "name": "SERENITY",
  "lat": 37.69175166666666,
  "lon": 23.881331666666664,
  "time_utc": "2026-07-14T02:31:57+00:00",
  "text": "SERENITY is underway at 7 knots near open water (37.692, 23.881), heading northwest."
 },
 {
  "id": "status-538008779",
  "type": "vessel_status",
  "mmsi": 538008779,
  "name": "LIVADI",
  "lat": 37.349075,
  "lon": 23.98109,
  "time_utc": "2026-07-14T02:31:57+00:00",
  "text": "LIVADI is underway at 10 knots near open water (37.349, 23.981), heading southwest."
 }
]