[
 {
  "id": "status-210965000",
  "type": "vessel_status",
  "mmsi": 210965000,
  "name": "CHAMPIONSLEAGUEJET2",
  "lat": 37.95039666666666,
  "lon": 23.547031666666665,
  "time_utc": "2026-07-19T05:04:59+00:00",
  "text": "CHAMPIONSLEAGUEJET2 (high-speed craft) is moored at 2 km off Salamina (Paloukia)."
 },
 {
  "id": "status-212731000",
  "type": "vessel_status",
  "mmsi": 212731000,
  "name": "MAGIC 2",
  "lat": 37.944493333333334,
  "lon": 23.640196666666668,
  "time_utc": "2026-07-19T05:04:59+00:00",
  "text": "MAGIC 2 (high-speed craft) is stationary at Piraeus. Reported destination: ARGOSARONIKOS."
 },
 {
  "id": "status-212769000",
  "type": "vessel_status",
  "mmsi": 212769000,
  "name": "MAGIC 3",
  "lat": 37.94344666666667,
  "lon": 23.643073333333334,
  "time_utc": "2026-07-19T05:04:59+00:00",
  "text": "MAGIC 3 (high-speed craft) is stationary at Piraeus. Reported destination: ARGOSARONIKOS."
 },
 {
  "id": "status-232014927",
  "type": "vessel_status",
  "mmsi": 232014927,
  "name": "YOUNAN",
  "lat": 37.93113166666667,
  "lon": 23.68337166666667,
  "time_utc": "2026-07-19T05:04:59+00:00",
  "text": "YOUNAN (pleasure) is stationary at 4 km off Piraeus."
 },
 {
  "id": "status-232193000",
  "type": "vessel_status",
  "mmsi": 232193000,
  "name": "M/Y VARMAR-VE",
  "lat": 37.930868333333336,
  "lon": 23.6828,
  "time_utc": "2026-07-19T05:04:59+00:00",
  "text": "M/Y VARMAR-VE (passenger) is stationary at 4 km off Piraeus. Reported destination: ARG/KOS."
 },
 {
  "id": "status-237009900",
  "type": "vessel_status",
  "mmsi": 237009900,
  "name": "MELINA II",
  "lat": 38.03122333333333,
  "lon": 23.59349166666667,
  "time_utc": "2026-07-19T05:04:59+00:00",
  "text": "MELINA II (cargo) is moored at 5 km off Elefsina. Reported destination: ASPROPIRGOS."
 },
 {
  "id": "status-237562900",
  "type": "vessel_status",
  "mmsi": 237562900,
  "name": "AGIOS ELEFTHERIOS IV",
  "lat": 37.9602,
  "lon": 23.54365,
  "time_utc": "2026-07-19T05:04:59+00:00",
  "text": "AGIOS ELEFTHERIOS IV (passenger) is underway at 8 knots near 1 km off Salamina (Paloukia), heading west. Reported destination: PERAMA-PALOYKIA."
 },
 {
  "id": "status-239414100",
  "type": "vessel_status",
  "mmsi": 239414100,
  "name": "SALAMINOMAHOS",
  "lat": 37.96516333333333,
  "lon": 23.529651666666666,
  "time_utc": "2026-07-19T05:04:59+00:00",
  "text": "SALAMINOMAHOS is stationary at Salamina (Paloukia). Reported destination: PERAMA-PALOYKIA."
 },
 {
  "id": "status-240039100",
  "type": "vessel_status",
  "mmsi": 240039100,
  "name": "CAPTAIN DIAMANTIS",
  "lat": 38.01956666666667,
  "lon": 23.548316666666665,
  "time_utc": "2026-07-19T05:04:59+00:00",
  "text": "CAPTAIN DIAMANTIS (cargo) is stationary at 2 km off Elefsina. Reported destination: ELEFSINA."
 },
 {
  "id": "status-240086700",
  "type": "vessel_status",
  "mmsi": 240086700,
  "name": "VESSY",
  "lat": 37.72182166666666,
  "lon": 23.385875,
  "time_utc": "2026-07-19T05:04:59+00:00",
  "text": "VESSY (sailing) is stationary at 3 km off Agistri (Skala)."
 },
 {
  "id": "status-240667400",
  "type": "vessel_status",
  "mmsi": 240667400,
  "name": "ANASTASIA K III",
  "lat": 37.9606,
  "lon": 23.571483333333333,
  "time_utc": "2026-07-19T05:04:59+00:00",
  "text": "ANASTASIA K III (cargo) is stationary at Perama. Reported destination: ELEFSINA."
 },
 {
  "id": "status-240676800",
  "type": "vessel_status",
  "mmsi": 240676800,
  "name": "LADY M",
  "lat": 37.91219,
  "lon": 23.706905,
  "time_utc": "2026-07-19T05:04:59+00:00",
  "text": "LADY M (sailing) is stationary at 7 km off Piraeus."
 },
 {
  "id": "status-240679700",
  "type": "vessel_status",
  "mmsi": 240679700,
  "name": "RIVIERA",
  "lat": 37.770338333333335,
  "lon": 23.576895,
  "time_utc": "2026-07-19T05:04:59+00:00",
  "text": "RIVIERA (sailing) is underway at 6 knots near open water (37.770, 23.577), heading south."
 },
 {
  "id": "status-240706400",
  "type": "vessel_status",
  "mmsi": 240706400,
  "name": "WHISPER",
  "lat": 37.913914999999996,
  "lon": 23.70211833333333,
  "time_utc": "2026-07-19T05:04:59+00:00",
  "text": "WHISPER (sailing) is moored at 7 km off Piraeus. Reported destination: ATHENS (ALIMOS)."
 },
 {
  "id": "status-240752600",
  "type": "vessel_status",
  "mmsi": 240752600,
  "name": "ALEXANDRA G",
  "lat": 37.96185333333334,
  "lon": 23.567661666666666,
  "time_utc": "2026-07-19T05:04:59+00:00",
  "text": "ALEXANDRA G (tanker) is stationary at Perama. Reported destination: PIRAEUS."
 },
 {
  "id": "status-240796900",
  "type": "vessel_status",
  "mmsi": 240796900,
  "name": "SEALINK VII",
  "lat": 37.74529333333333,
  "lon": 23.429165,
  "time_utc": "2026-07-19T05:04:59+00:00",
  "text": "SEALINK VII (pleasure) was last heard near Aegina."
 },
 {
  "id": "status-240871000",
  "type": "vessel_status",
  "mmsi": 240871000,
  "name": "ECOBREEZE",
  "lat": 38.037195,
  "lon": 23.53320666666667,
  "time_utc": "2026-07-19T05:04:59+00:00",
  "text": "ECOBREEZE (tanker) is stationary at Elefsina."
 },
 {
  "id": "status-240897000",
  "type": "vessel_status",
  "mmsi": 240897000,
  "name": "AEGEAN ACE",
  "lat": 38.037445000000005,
  "lon": 23.533586666666668,
  "time_utc": "2026-07-19T05:04:59+00:00",
  "text": "AEGEAN ACE (tanker) is stationary at Elefsina. Reported destination: PERIOHI."
 },
 {
  "id": "status-240985000",
  "type": "vessel_status",
  "mmsi": 240985000,
  "name": "RHINO",
  "lat": 37.947015,
  "lon": 23.555515,
  "time_utc": "2026-07-19T05:04:59+00:00",
  "text": "RHINO (cargo) is stationary at 2 km off Perama. Reported destination: GRSAL."
 },
 {
  "id": "status-241588000",
  "type": "vessel_status",
  "mmsi": 241588000,
  "name": "CHRISTOS XLVI",
  "lat": 37.95364333333334,
  "lon": 23.55154,
  "time_utc": "2026-07-19T05:04:59+00:00",
  "text": "CHRISTOS XLVI (special craft) is stationary at 2 km off Perama. Reported destination: PIRAEUS."
 },
 {
  "id": "status-241634000",
  "type": "vessel_status",
  "mmsi": 241634000,
  "name": "KAPETAN MICHALIS",
  "lat": 37.96041833333334,
  "lon": 23.577650000000002,
  "time_utc": "2026-07-19T05:04:59+00:00",
  "text": "KAPETAN MICHALIS (tanker) is stationary at 1 km off Perama. Reported destination: BUNKERING_PIRAEUS."
 },
 {
  "id": "status-241654000",
  "type": "vessel_status",
  "mmsi": 241654000,
  "name": "APTERA",
  "lat": 37.91731166666667,
  "lon": 23.56433333333333,
  "time_utc": "2026-07-19T05:04:59+00:00",
  "text": "APTERA (tanker) is at anchor at Piraeus anchorage. Reported destination: GRPIR."
 },
 {
  "id": "status-241802000",
  "type": "vessel_status",
  "mmsi": 241802000,
  "name": "AERO 1 HIGHSPEED",
  "lat": 37.942789999999995,
  "lon": 23.642346666666665,
  "time_utc": "2026-07-19T05:04:59+00:00",
  "text": "AERO 1 HIGHSPEED (high-speed craft) is stationary at Piraeus. Reported destination: ARGOSARONIKOS."
 },
 {
  "id": "status-241803000",
  "type": "vessel_status",
  "mmsi": 241803000,
  "name": "AERO 2 HIGHSPEED",
  "lat": 37.94287,
  "lon": 23.641866666666665,
  "time_utc": "2026-07-19T05:04:59+00:00",
  "text": "AERO 2 HIGHSPEED (high-speed craft) is moored at Piraeus. Reported destination: SARONIKOS."
 },
 {
  "id": "status-241911000",
  "type": "vessel_status",
  "mmsi": 241911000,
  "name": "CAPTAIN GIANNIS P.",
  "lat": 37.943729999999995,
  "lon": 23.631956666666667,
  "time_utc": "2026-07-19T05:04:59+00:00",
  "text": "CAPTAIN GIANNIS P. (special craft) is stationary at Piraeus. Reported destination: GRPIR."
 },
 {
  "id": "status-241951000",
  "type": "vessel_status",
  "mmsi": 241951000,
  "name": "SVS II",
  "lat": 38.03603333333333,
  "lon": 23.506175,
  "time_utc": "2026-07-19T05:04:59+00:00",
  "text": "SVS II (tug/tow) is moored at Elefsis Bay anchorage. Reported destination: PIRAEUS."
 },
 {
  "id": "status-241972000",
  "type": "vessel_status",
  "mmsi": 241972000,
  "name": "REA",
  "lat": 37.956558333333334,
  "lon": 23.60379,
  "time_utc": "2026-07-19T05:04:59+00:00",
  "text": "REA (special craft) is underway at 6 knots near 3 km off Piraeus, heading southeast. Reported destination: PIRAEUS."
 },
 {
  "id": "status-241975000",
  "type": "vessel_status",
  "mmsi": 241975000,
  "name": "LYBOUSSAKIS TAXIARCH",
  "lat": 37.957361666666664,
  "lon": 23.610586666666666,
  "time_utc": "2026-07-19T05:04:59+00:00",
  "text": "LYBOUSSAKIS TAXIARCH (special craft) is stationary at 3 km off Piraeus. Reported destination: KERATSINI."
 },
 {
  "id": "status-247048150",
  "type": "vessel_status",
  "mmsi": 247048150,
  "name": "BOUKI",
  "lat": 37.930868333333336,
  "lon": 23.684338333333336,
  "time_utc": "2026-07-19T05:04:59+00:00",
  "text": "BOUKI (pleasure) is stationary at 4 km off Piraeus."
 },
 {
  "id": "status-256911000",
  "type": "vessel_status",
  "mmsi": 256911000,
  "name": "MADO",
  "lat": 37.911653333333334,
  "lon": 23.702341666666666,
  "time_utc": "2026-07-19T05:04:59+00:00",
  "text": "MADO (pleasure) is moored at 7 km off Piraeus. Reported destination: IONIAN."
 },
 {
  "id": "status-319012900",
  "type": "vessel_status",
  "mmsi": 319012900,
  "name": "RADIANT",
  "lat": 37.93477666666667,
  "lon": 23.681688333333334,
  "time_utc": "2026-07-19T05:04:59+00:00",
  "text": "RADIANT (pleasure) is moored at 4 km off Piraeus. Reported destination: ATHENS GR."
 },
 {
  "id": "status-319119400",
  "type": "vessel_status",
  "mmsi": 319119400,
  "name": "LADY LILIAN",
  "lat": 37.802299999999995,
  "lon": 23.773711666666667,
  "time_utc": "2026-07-19T05:04:59+00:00",
  "text": "LADY LILIAN (pleasure) is moored at open water (37.802, 23.774). Reported destination: VOULIAGMENI."
 },
 {
  "id": "status-319255000",
  "type": "vessel_status",
  "mmsi": 319255000,
  "name": "SAHAB IV",
  "lat": 37.92902,
  "lon": 23.683463333333336,
  "time_utc": "2026-07-19T05:04:59+00:00",
  "text": "SAHAB IV (pleasure) is moored at 4 km off Piraeus. Reported destination: FLISVOS.PIRAEUS."
 },
 {
  "id": "status-319650000",
  "type": "vessel_status",
  "mmsi": 319650000,
  "name": "ALWAELI",
  "lat": 37.92995833333334,
  "lon": 23.681515,
  "time_utc": "2026-07-19T05:04:59+00:00",
  "text": "ALWAELI (pleasure) is moored at 4 km off Piraeus. Reported destination: GR."
 },
 {
  "id": "status-341166001",
  "type": "vessel_status",
  "mmsi": 341166001,
  "name": "TO CALLISTO",
  "lat": 37.960501666666666,
  "lon": 23.575651666666666,
  "time_utc": "2026-07-19T05:04:59+00:00",
  "text": "TO CALLISTO (passenger) is stationary at 1 km off Perama. Reported destination: PIRAEUS."
 },
 {
  "id": "status-368380010",
  "type": "vessel_status",
  "mmsi": 368380010,
  "name": "GRACE",
  "lat": 37.504178333333336,
  "lon": 23.450091666666665,
  "time_utc": "2026-07-19T05:04:59+00:00",
  "text": "GRACE is stationary at Poros."
 },
 {
  "id": "status-376038000",
  "type": "vessel_status",
  "mmsi": 376038000,
  "name": "NORTHWIND II",
  "lat": 37.96187666666666,
  "lon": 23.491331666666667,
  "time_utc": "2026-07-19T05:04:59+00:00",
  "text": "NORTHWIND II (pleasure) is stationary at 4 km off Salamina (Paloukia). Reported destination: ZEA MARINA."
 },
 {
  "id": "status-378001221",
  "type": "vessel_status",
  "mmsi": 378001221,
  "name": "MARLA II",
  "lat": 37.271123333333335,
  "lon": 23.150648333333333,
  "time_utc": "2026-07-19T05:04:59+00:00",
  "text": "MARLA II (pleasure) is moored at Spetses. Reported destination: PIRAEUS."
 },
 {
  "id": "status-631010093",
  "type": "vessel_status",
  "mmsi": 631010093,
  "name": "ICE",
  "lat": 37.95252,
  "lon": 23.55303,
  "time_utc": "2026-07-19T05:04:59+00:00",
  "text": "ICE (pleasure) is moored at 2 km off Perama. Reported destination: GRPIR."
 },
 {
  "id": "status-636011267",
  "type": "vessel_status",
  "mmsi": 636011267,
  "name": "MARIANNA V.V.",
  "lat": 37.85648833333333,
  "lon": 23.5366,
  "time_utc": "2026-07-19T05:04:59+00:00",
  "text": "MARIANNA V.V. (tanker) is at anchor at open water (37.856, 23.537). Reported destination: GR PIR."
 },
 {
  "id": "status-230052180",
  "type": "vessel_status",
  "mmsi": 230052180,
  "name": "INSPIRATION",
  "lat": 37.928916666666666,
  "lon": 23.683249999999997,
  "time_utc": "2026-07-19T05:04:59+00:00",
  "text": "INSPIRATION (pleasure) is moored at 4 km off Piraeus. Reported destination: AEGEAN SEA."
 },
 {
  "id": "status-232063333",
  "type": "vessel_status",
  "mmsi": 232063333,
  "name": "LA BELLA LYNN",
  "lat": 38.03159,
  "lon": 23.549756666666667,
  "time_utc": "2026-07-19T05:04:59+00:00",
  "text": "LA BELLA LYNN is stationary at Elefsina."
 },
 {
  "id": "status-237787800",
  "type": "vessel_status",
  "mmsi": 237787800,
  "name": "PAREA",
  "lat": 37.96015666666666,
  "lon": 23.57415,
  "time_utc": "2026-07-19T05:04:59+00:00",
  "text": "PAREA (sailing) is moored at Perama. Reported destination: SEA TRIALS."
 },
 {
  "id": "status-239998600",
  "type": "vessel_status",
  "mmsi": 239998600,
  "name": "ACCORD",
  "lat": 38.02865,
  "lon": 23.59398333333333,
  "time_utc": "2026-07-19T05:04:59+00:00",
  "text": "ACCORD (tanker) is stationary at 5 km off Elefsina. Reported destination: ELEFSIS."
 },
 {
  "id": "status-240013300",
  "type": "vessel_status",
  "mmsi": 240013300,
  "name": "SUN ANEMOS",
  "lat": 37.87734833333333,
  "lon": 23.725483333333333,
  "time_utc": "2026-07-19T05:04:59+00:00",
  "text": "SUN ANEMOS is stationary at open water (37.877, 23.725). Reported destination: SPETSES."
 },
 {
  "id": "status-240013900",
  "type": "vessel_status",
  "mmsi": 240013900,
  "name": "STRATOS",
  "lat": 38.028985,
  "lon": 23.59576333333333,
  "time_utc": "2026-07-19T05:04:59+00:00",
  "text": "STRATOS (special craft) is stationary at 5 km off Elefsina. Reported destination: PIRAEUS."
 },
 {
  "id": "status-240260100",
  "type": "vessel_status",
  "mmsi": 240260100,
  "name": "IROULA",
  "lat": 37.78004166666666,
  "lon": 23.77710666666667,
  "time_utc": "2026-07-19T05:04:59+00:00",
  "text": "IROULA (sailing) is underway at 7 knots near open water (37.780, 23.777), heading southeast."
 },
 {
  "id": "status-240398300",
  "type": "vessel_status",
  "mmsi": 240398300,
  "name": "THEION",
  "lat": 37.518005,
  "lon": 23.43157,
  "time_utc": "2026-07-19T05:04:59+00:00",
  "text": "THEION (pleasure) is at anchor at 3 km off Poros. Reported destination: AGIOS KOSMAS."
 },
 {
  "id": "status-241011000",
  "type": "vessel_status",
  "mmsi": 241011000,
  "name": "CHRISTOS XXI",
  "lat": 38.02908,
  "lon": 23.595824999999998,
  "time_utc": "2026-07-19T05:04:59+00:00",
  "text": "CHRISTOS XXI (special craft) is stationary at 5 km off Elefsina. Reported destination: PIRAEUS."
 },
 {
  "id": "status-241067000",
  "type": "vessel_status",
  "mmsi": 241067000,
  "name": "SANJANA",
  "lat": 37.93095,
  "lon": 23.6488,
  "time_utc": "2026-07-19T05:04:59+00:00",
  "text": "SANJANA (pleasure) is moored at Piraeus. Reported destination: SARONIKOS."
 },
 {
  "id": "status-241349000",
  "type": "vessel_status",
  "mmsi": 241349000,
  "name": "VERONIKI IV",
  "lat": 38.020554999999995,
  "lon": 23.540956666666666,
  "time_utc": "2026-07-19T05:04:59+00:00",
  "text": "VERONIKI IV (tanker) is at anchor at 2 km off Elefsina. Reported destination: GREEU."
 },
 {
  "id": "status-241442000",
  "type": "vessel_status",
  "mmsi": 241442000,
  "name": "PANTANASSA",
  "lat": 38.024559999999994,
  "lon": 23.591738333333335,
  "time_utc": "2026-07-19T05:04:59+00:00",
  "text": "PANTANASSA (special craft) is at anchor at 5 km off Elefsina. Reported destination: PIRAEUS."
 },
 {
  "id": "status-241672000",
  "type": "vessel_status",
  "mmsi": 241672000,
  "name": "SMYRNA DI LEVANTE",
  "lat": 37.94108666666667,
  "lon": 23.625094999999998,
  "time_utc": "2026-07-19T05:04:59+00:00",
  "text": "SMYRNA DI LEVANTE (passenger) is stationary at Piraeus. Reported destination: GRPIR."
 },
 {
  "id": "status-241675000",
  "type": "vessel_status",
  "mmsi": 241675000,
  "name": "KOHYLI",
  "lat": 38.037371666666665,
  "lon": 23.533653333333334,
  "time_utc": "2026-07-19T05:04:59+00:00",
  "text": "KOHYLI (tanker) is stationary at Elefsina. Reported destination: PERIOXI."
 },
 {
  "id": "status-241728000",
  "type": "vessel_status",
  "mmsi": 241728000,
  "name": "PANORMITIS",
  "lat": 37.958346666666664,
  "lon": 23.561913333333333,
  "time_utc": "2026-07-19T05:04:59+00:00",
  "text": "PANORMITIS (special craft) is underway at 1 knots near Perama, heading northeast. Reported destination: PIRAEUS."
 },
 {
  "id": "status-241804000",
  "type": "vessel_status",
  "mmsi": 241804000,
  "name": "AERO 3 HIGHSPEED",
  "lat": 37.94295666666667,
  "lon": 23.641328333333334,
  "time_utc": "2026-07-19T05:04:59+00:00",
  "text": "AERO 3 HIGHSPEED (high-speed craft) is moored at Piraeus. Reported destination: SARONIKOS."
 },
 {
  "id": "status-241903000",
  "type": "vessel_status",
  "mmsi": 241903000,
  "name": "DON'T WORRY",
  "lat": 37.940918333333336,
  "lon": 23.670395,
  "time_utc": "2026-07-19T05:04:59+00:00",
  "text": "DON'T WORRY (pleasure) is moored at 3 km off Piraeus. Reported destination: PIRAEUS."
 },
 {
  "id": "status-244002920",
  "type": "vessel_status",
  "mmsi": 244002920,
  "name": "OUT OF THE BLUE",
  "lat": 37.87528,
  "lon": 23.727073333333333,
  "time_utc": "2026-07-19T05:04:59+00:00",
  "text": "OUT OF THE BLUE (pleasure) is stationary at open water (37.875, 23.727)."
 },
 {
  "id": "status-248874000",
  "type": "vessel_status",
  "mmsi": 248874000,
  "name": "TOY\\A",
  "lat": 37.524915,
  "lon": 23.42057,
  "time_utc": "2026-07-19T05:04:59+00:00",
  "text": "TOY\\A (pleasure) is underway at 9 knots near 4 km off Poros, heading north. Reported destination: AEGEAN SEA."
 },
 {
  "id": "status-256002020",
  "type": "vessel_status",
  "mmsi": 256002020,
  "name": "SHALIMAR II",
  "lat": 37.93132333333333,
  "lon": 23.68046,
  "time_utc": "2026-07-19T05:04:59+00:00",
  "text": "SHALIMAR II is stationary at 4 km off Piraeus."
 },
 {
  "id": "status-356324000",
  "type": "vessel_status",
  "mmsi": 356324000,
  "name": "SUNLIT",
  "lat": 37.94923333333334,
  "lon": 23.6001,
  "time_utc": "2026-07-19T05:04:59+00:00",
  "text": "SUNLIT (tanker) is stationary at 3 km off Piraeus. Reported destination: PIRAEUS."
 },
 {
  "id": "status-605016420",
  "type": "vessel_status",
  "mmsi": 605016420,
  "name": "BADJI MOKHTAR III",
  "lat": 38.02836666666667,
  "lon": 23.497225,
  "time_utc": "2026-07-19T05:04:59+00:00",
  "text": "BADJI MOKHTAR III (passenger) is moored at Elefsis Bay anchorage. Reported destination: GRE ELEFSIS."
 },
 {
  "id": "status-232049819",
  "type": "vessel_status",
  "mmsi": 232049819,
  "name": "QUANTUM BLUE",
  "lat": 37.93656166666666,
  "lon": 23.661485000000003,
  "time_utc": "2026-07-19T05:04:59+00:00",
  "text": "QUANTUM BLUE (pleasure) is stationary at 2 km off Piraeus."
 },
 {
  "id": "status-237021400",
  "type": "vessel_status",
  "mmsi": 237021400,
  "name": "AG NEKTARIOS AIGINAS",
  "lat": 37.944248333333334,
  "lon": 23.64232333333333,
  "time_utc": "2026-07-19T05:04:59+00:00",
  "text": "AG NEKTARIOS AIGINAS is stationary at Piraeus. Reported destination: PIRAIAS."
 },
 {
  "id": "status-237041100",
  "type": "vessel_status",
  "mmsi": 237041100,
  "name": "PROTUG 18",
  "lat": 37.951233333333334,
  "lon": 23.548735,
  "time_utc": "2026-07-19T05:04:59+00:00",
  "text": "PROTUG 18 (special craft) is stationary at 2 km off Salamina (Paloukia). Reported destination: SALAMIS."
 },
 {
  "id": "status-237082600",
  "type": "vessel_status",
  "mmsi": 237082600,
  "name": "ZOI",
  "lat": 37.269733333333335,
  "lon": 23.154549999999997,
  "time_utc": "2026-07-19T05:04:59+00:00",
  "text": "ZOI (pleasure) is moored at Spetses. Reported destination: AGIOS KOSMAS."
 },
 {
  "id": "status-237500621",
  "type": "vessel_status",
  "mmsi": 237500621,
  "name": "IGNATIOS XXI",
  "lat": 37.933953333333335,
  "lon": 23.61818333333333,
  "time_utc": "2026-07-19T05:04:59+00:00",
  "text": "IGNATIOS XXI (special craft) is stationary at 2 km off Piraeus."
 },
 {
  "id": "status-240338800",
  "type": "vessel_status",
  "mmsi": 240338800,
  "name": "ANEMA",
  "lat": 37.69042666666667,
  "lon": 23.45,
  "time_utc": "2026-07-19T05:04:59+00:00",
  "text": "ANEMA (sailing) is at anchor at 6 km off Aegina. Reported destination: MARINA ALIMOS."
 },
 {
  "id": "status-240680600",
  "type": "vessel_status",
  "mmsi": 240680600,
  "name": "SWELL",
  "lat": 37.51844833333334,
  "lon": 23.395958333333333,
  "time_utc": "2026-07-19T05:04:59+00:00",
  "text": "SWELL (sailing) is stationary at 6 km off Poros."
 },
 {
  "id": "status-240695400",
  "type": "vessel_status",
  "mmsi": 240695400,
  "name": "MOMMY POMMY",
  "lat": 37.85239833333333,
  "lon": 23.65834,
  "time_utc": "2026-07-19T05:04:59+00:00",
  "text": "MOMMY POMMY is underway at 7 knots near open water (37.852, 23.658), heading southwest."
 },
 {
  "id": "status-241925000",
  "type": "vessel_status",
  "mmsi": 241925000,
  "name": "CHRISTOS 73",
  "lat": 37.95227333333333,
  "lon": 23.551933333333334,
  "time_utc": "2026-07-19T05:04:59+00:00",
  "text": "CHRISTOS 73 (special craft) is stationary at 2 km off Perama. Reported destination: GRPER."
 },
 {
  "id": "status-248472000",
  "type": "vessel_status",
  "mmsi": 248472000,
  "name": "SIDER LION",
  "lat": 38.04150666666667,
  "lon": 23.530326666666667,
  "time_utc": "2026-07-19T05:04:59+00:00",
  "text": "SIDER LION (cargo) is moored at Elefsina. Reported destination: GREEU."
 },
 {
  "id": "status-511100847",
  "type": "vessel_status",
  "mmsi": 511100847,
  "name": "CORAL",
  "lat": 37.936744999999995,
  "lon": 23.649951666666666,
  "time_utc": "2026-07-19T05:04:59+00:00",
  "text": "CORAL (pleasure) is stationary at Piraeus. Reported destination: ZEA MARINA  PIRAEUS."
 },
 {
  "id": "status-240334100",
  "type": "vessel_status",
  "mmsi": 240334100,
  "name": "OVAL",
  "lat": 37.93376666666666,
  "lon": 23.64894333333333,
  "time_utc": "2026-07-19T05:04:59+00:00",
  "text": "OVAL (pleasure) is moored at Piraeus. Reported destination: ZEA."
 },
 {
  "id": "status-240671400",
  "type": "vessel_status",
  "mmsi": 240671400,
  "name": "OKIALOS",
  "lat": 37.86045333333333,
  "lon": 23.546218333333336,
  "time_utc": "2026-07-19T05:04:59+00:00",
  "text": "OKIALOS (passenger) is underway at 13 knots near open water (37.860, 23.546), heading southwest. Reported destination: P-A-P."
 },
 {
  "id": "status-241585000",
  "type": "vessel_status",
  "mmsi": 241585000,
  "name": "CH.GEMITZOGLOU",
  "lat": 38.02448833333334,
  "lon": 23.591594999999998,
  "time_utc": "2026-07-19T05:04:59+00:00",
  "text": "CH.GEMITZOGLOU (special craft) is stationary at 5 km off Elefsina. Reported destination: PIRAEUS."
 },
 {
  "id": "status-352001122",
  "type": "vessel_status",
  "mmsi": 352001122,
  "name": "AYA M",
  "lat": 37.89986,
  "lon": 23.545728333333333,
  "time_utc": "2026-07-19T05:04:59+00:00",
  "text": "AYA M (cargo) is at anchor at Piraeus anchorage. Reported destination: GR PIR."
 },
 {
  "id": "status-210227000",
  "type": "vessel_status",
  "mmsi": 210227000,
  "name": "ARIA 1",
  "lat": 37.27013833333333,
  "lon": 23.154428333333332,
  "time_utc": "2026-07-19T05:04:59+00:00",
  "text": "ARIA 1 (sailing) is moored at Spetses. Reported destination: ZEA."
 },
 {
  "id": "status-240123500",
  "type": "vessel_status",
  "mmsi": 240123500,
  "name": "DELTA",
  "lat": 37.91261833333333,
  "lon": 23.702158333333333,
  "time_utc": "2026-07-19T05:04:59+00:00",
  "text": "DELTA (sailing) is stationary at 7 km off Piraeus."
 },
 {
  "id": "status-240154600",
  "type": "vessel_status",
  "mmsi": 240154600,
  "name": "DEEP WATER",
  "lat": 37.91201,
  "lon": 23.705666666666666,
  "time_utc": "2026-07-19T05:04:59+00:00",
  "text": "DEEP WATER (sailing) is stationary at 7 km off Piraeus."
 },
 {
  "id": "status-241938000",
  "type": "vessel_status",
  "mmsi": 241938000,
  "name": "ANDROS KING",
  "lat": 38.00629833333333,
  "lon": 24.091001666666667,
  "time_utc": "2026-07-19T05:04:59+00:00",
  "text": "ANDROS KING (passenger) is underway at 19 knots near 7 km off Rafina, heading east. Reported destination: GR_RAFINA."
 },
 {
  "id": "status-241997000",
  "type": "vessel_status",
  "mmsi": 241997000,
  "name": "AXOS",
  "lat": 37.92035333333333,
  "lon": 23.053980000000003,
  "time_utc": "2026-07-19T05:04:59+00:00",
  "text": "AXOS (special craft) is stationary at 4 km off Corinth Canal (Isthmia). Reported destination: AGIO THEODOROI."
 },
 {
  "id": "status-244690035",
  "type": "vessel_status",
  "mmsi": 244690035,
  "name": "BONTEKONING",
  "lat": 37.914093333333334,
  "lon": 23.703809999999997,
  "time_utc": "2026-07-19T05:04:59+00:00",
  "text": "BONTEKONING (sailing) is stationary at 7 km off Piraeus. Reported destination: ATHENE."
 },
 {
  "id": "status-319020000",
  "type": "vessel_status",
  "mmsi": 319020000,
  "name": "LIGHTNING",
  "lat": 37.93383666666667,
  "lon": 23.681496666666664,
  "time_utc": "2026-07-19T05:04:59+00:00",
  "text": "LIGHTNING (pleasure) is moored at 4 km off Piraeus. Reported destination: GRPIR."
 },
 {
  "id": "status-368199550",
  "type": "vessel_status",
  "mmsi": 368199550,
  "name": "H2O",
  "lat": 37.93653,
  "lon": 23.661746666666666,
  "time_utc": "2026-07-19T05:04:59+00:00",
  "text": "H2O is stationary at 2 km off Piraeus."
 },
 {
  "id": "status-377465000",
  "type": "vessel_status",
  "mmsi": 377465000,
  "name": "CHRISTOS XXVI",
  "lat": 37.951710000000006,
  "lon": 23.548521666666666,
  "time_utc": "2026-07-19T05:04:59+00:00",
  "text": "CHRISTOS XXVI (cargo) is moored at 2 km off Salamina (Paloukia). Reported destination: GR_PIR_."
 },
 {
  "id": "status-428711000",
  "type": "vessel_status",
  "mmsi": 428711000,
  "name": "THE ANGELS",
  "lat": 37.74553166666667,
  "lon": 23.429073333333335,
  "time_utc": "2026-07-19T05:04:59+00:00",
  "text": "THE ANGELS (sailing) is underway at 1 knots near Aegina."
 },
 {
  "id": "status-240025700",
  "type": "vessel_status",
  "mmsi": 240025700,
  "name": "CHRISTOS XL",
  "lat": 37.950871666666664,
  "lon": 23.548676666666665,
  "time_utc": "2026-07-19T05:04:59+00:00",
  "text": "CHRISTOS XL (special craft) is stationary at 2 km off Salamina (Paloukia). Reported destination: ELEFSINA."
 },
 {
  "id": "status-248771000",
  "type": "vessel_status",
  "mmsi": 248771000,
  "name": "MY FAN TOO",
  "lat": 37.26179,
  "lon": 23.16458,
  "time_utc": "2026-07-19T05:04:59+00:00",
  "text": "MY FAN TOO (pleasure) is stationary at Spetses. Reported destination: SPETSES."
 },
 {
  "id": "status-235077171",
  "type": "vessel_status",
  "mmsi": 235077171,
  "name": "MY LOVE",
  "lat": 37.26159666666667,
  "lon": 23.164505000000002,
  "time_utc": "2026-07-19T05:04:59+00:00",
  "text": "MY LOVE is stationary at Spetses."
 },
 {
  "id": "status-240619700",
  "type": "vessel_status",
  "mmsi": 240619700,
  "name": "PERLA",
  "lat": 37.913201666666666,
  "lon": 23.701228333333333,
  "time_utc": "2026-07-19T05:04:59+00:00",
  "text": "PERLA (sailing) is stationary at 7 km off Piraeus."
 },
 {
  "id": "status-241012000",
  "type": "vessel_status",
  "mmsi": 241012000,
  "name": "CHRISTOS XX",
  "lat": 38.03635,
  "lon": 23.508233333333333,
  "time_utc": "2026-07-19T05:04:59+00:00",
  "text": "CHRISTOS XX is stationary at Elefsis Bay anchorage."
 },
 {
  "id": "status-341548001",
  "type": "vessel_status",
  "mmsi": 341548001,
  "name": "BRUNSWICK",
  "lat": 37.938006666666666,
  "lon": 23.648101666666665,
  "time_utc": "2026-07-19T05:04:59+00:00",
  "text": "BRUNSWICK (pleasure) is stationary at Piraeus."
 },
 {
  "id": "status-240125500",
  "type": "vessel_status",
  "mmsi": 240125500,
  "name": "MARGARITA",
  "lat": 37.915075,
  "lon": 23.701408333333333,
  "time_utc": "2026-07-19T05:04:59+00:00",
  "text": "MARGARITA (sailing) is stationary at 6 km off Piraeus."
 },
 {
  "id": "status-240601900",
  "type": "vessel_status",
  "mmsi": 240601900,
  "name": "PROTOPOROS XVII",
  "lat": 37.965648333333334,
  "lon": 23.530353333333334,
  "time_utc": "2026-07-19T05:04:59+00:00",
  "text": "PROTOPOROS XVII (passenger) is stationary at Salamina (Paloukia). Reported destination: PALOUKIA PERAMA."
 },
 {
  "id": "status-255902680",
  "type": "vessel_status",
  "mmsi": 255902680,
  "name": "LADY MALAK",
  "lat": 37.93863666666667,
  "lon": 23.648778333333333,
  "time_utc": "2026-07-19T05:04:59+00:00",
  "text": "LADY MALAK (pleasure) is moored at Piraeus. Reported destination: ZEA MARINA."
 },
 {
  "id": "status-237529000",
  "type": "vessel_status",
  "mmsi": 237529000,
  "name": "AEGAEO",
  "lat": 37.94023,
  "lon": 23.62253666666667,
  "time_utc": "2026-07-19T05:04:59+00:00",
  "text": "AEGAEO is moored at Piraeus. Reported destination: PIRAEUS."
 },
 {
  "id": "status-239658000",
  "type": "vessel_status",
  "mmsi": 239658000,
  "name": "HYPERSPEED JET 4",
  "lat": 37.83575,
  "lon": 23.623116666666665,
  "time_utc": "2026-07-19T05:04:59+00:00",
  "text": "HYPERSPEED JET 4 (high-speed craft) is underway at 35 knots near open water (37.836, 23.623), heading south. Reported destination: SERIFO-SIFNO-MILO."
 },
 {
  "id": "status-229045000",
  "type": "vessel_status",
  "mmsi": 229045000,
  "name": "M/Y LA PELLEGRINA 1",
  "lat": 37.960429999999995,
  "lon": 23.570058333333336,
  "time_utc": "2026-07-19T05:04:59+00:00",
  "text": "M/Y LA PELLEGRINA 1 (pleasure) is moored at Perama. Reported destination: SARONIC."
 },
 {
  "id": "status-232060738",
  "type": "vessel_status",
  "mmsi": 232060738,
  "name": "PLAYMAKER",
  "lat": 37.51109333333333,
  "lon": 23.442486666666664,
  "time_utc": "2026-07-19T05:04:59+00:00",
  "text": "PLAYMAKER (sailing) is stationary at 2 km off Poros."
 },
 {
  "id": "status-237044600",
  "type": "vessel_status",
  "mmsi": 237044600,
  "name": "EKATERINI P.",
  "lat": 38.02397166666666,
  "lon": 24.012083333333333,
  "time_utc": "2026-07-19T05:04:59+00:00",
  "text": "EKATERINI P. (passenger) is stationary at Rafina. Reported destination: R-P-N-M-T-R."
 },
 {
  "id": "status-240787100",
  "type": "vessel_status",
  "mmsi": 240787100,
  "name": "AUGUST",
  "lat": 37.970436666666664,
  "lon": 23.36401,
  "time_utc": "2026-07-19T05:04:59+00:00",
  "text": "AUGUST is stationary at open water (37.970, 23.364)."
 },
 {
  "id": "status-240389000",
  "type": "vessel_status",
  "mmsi": 240389000,
  "name": "BLUE STAR MYCONOS",
  "lat": 37.672805000000004,
  "lon": 23.713241666666665,
  "time_utc": "2026-07-19T05:04:59+00:00",
  "text": "BLUE STAR MYCONOS (passenger) is underway at 24 knots near open water (37.673, 23.713), heading southeast. Reported destination: S-M-E-K-M-S-P."
 },
 {
  "id": "status-249226000",
  "type": "vessel_status",
  "mmsi": 249226000,
  "name": "IRAVATI",
  "lat": 37.291653333333336,
  "lon": 23.185173333333335,
  "time_utc": "2026-07-19T05:04:59+00:00",
  "text": "IRAVATI (pleasure) is underway at 5 knots near 4 km off Spetses, heading south. Reported destination: MARINA ATHINON."
 },
 {
  "id": "status-241611000",
  "type": "vessel_status",
  "mmsi": 241611000,
  "name": "KALIKRATIS",
  "lat": 37.915375000000004,
  "lon": 23.55337666666667,
  "time_utc": "2026-07-19T05:04:59+00:00",
  "text": "KALIKRATIS (tanker) is underway at 5 knots near Piraeus anchorage, heading south. Reported destination: GRPIR."
 },
 {
  "id": "status-237599400",
  "type": "vessel_status",
  "mmsi": 237599400,
  "name": "DESTINY",
  "lat": 37.93883833333334,
  "lon": 23.685553333333335,
  "time_utc": "2026-07-19T05:04:59+00:00",
  "text": "DESTINY is stationary at 4 km off Piraeus."
 },
 {
  "id": "status-240685000",
  "type": "vessel_status",
  "mmsi": 240685000,
  "name": "ELYROS",
  "lat": 37.947285,
  "lon": 23.637193333333336,
  "time_utc": "2026-07-19T05:04:59+00:00",
  "text": "ELYROS (passenger) is moored at Piraeus. Reported destination: SOUDA."
 },
 {
  "id": "status-241621000",
  "type": "vessel_status",
  "mmsi": 241621000,
  "name": "CHRISTOS XLII",
  "lat": 37.97796666666667,
  "lon": 23.549528333333335,
  "time_utc": "2026-07-19T05:04:59+00:00",
  "text": "CHRISTOS XLII (special craft) is underway at 3 knots near 2 km off Salamina (Paloukia), heading north. Reported destination: GR PIR."
 },
 {
  "id": "status-210741000",
  "type": "vessel_status",
  "mmsi": 210741000,
  "name": "AERO 4 HIGHSPEED",
  "lat": 37.498855000000006,
  "lon": 23.451533333333334,
  "time_utc": "2026-07-19T05:04:59+00:00",
  "text": "AERO 4 HIGHSPEED (high-speed craft) is stationary at Poros. Reported destination: SARONIKOS."
 },
 {
  "id": "status-237500000",
  "type": "vessel_status",
  "mmsi": 237500000,
  "name": "LINDOS",
  "lat": 37.26841666666667,
  "lon": 23.15705,
  "time_utc": "2026-07-19T05:04:59+00:00",
  "text": "LINDOS is moored at Spetses. Reported destination: SPETSES."
 },
 {
  "id": "status-239808200",
  "type": "vessel_status",
  "mmsi": 239808200,
  "name": "LEON",
  "lat": 38.034713333333336,
  "lon": 23.535104999999998,
  "time_utc": "2026-07-19T05:04:59+00:00",
  "text": "LEON (special craft) is underway at 5 knots near Elefsina, heading west."
 },
 {
  "id": "status-241600000",
  "type": "vessel_status",
  "mmsi": 241600000,
  "name": "PLATYTERA",
  "lat": 37.946131666666666,
  "lon": 23.58672,
  "time_utc": "2026-07-19T05:04:59+00:00",
  "text": "PLATYTERA (special craft) is underway at 7 knots near 3 km off Perama, heading southwest. Reported destination: GR PIR."
 },
 {
  "id": "status-241694000",
  "type": "vessel_status",
  "mmsi": 241694000,
  "name": "IOSIF K",
  "lat": 37.905408333333334,
  "lon": 23.617673333333336,
  "time_utc": "2026-07-19T05:04:59+00:00",
  "text": "IOSIF K (cargo) is underway at 1 knots near Piraeus anchorage, heading north. Reported destination: SOUDA."
 },
 {
  "id": "status-241792000",
  "type": "vessel_status",
  "mmsi": 241792000,
  "name": "VERNICOS SCAFI II",
  "lat": 38.02449,
  "lon": 23.591538333333332,
  "time_utc": "2026-07-19T05:04:59+00:00",
  "text": "VERNICOS SCAFI II (special craft) is stationary at 5 km off Elefsina. Reported destination: PIRAEUS."
 },
 {
  "id": "status-248175000",
  "type": "vessel_status",
  "mmsi": 248175000,
  "name": "ARESYA",
  "lat": 37.93902666666667,
  "lon": 23.669028333333333,
  "time_utc": "2026-07-19T05:04:59+00:00",
  "text": "ARESYA (pleasure) is stationary at 3 km off Piraeus."
 },
 {
  "id": "status-237448400",
  "type": "vessel_status",
  "mmsi": 237448400,
  "name": "KATERINA STAR",
  "lat": 37.29436333333333,
  "lon": 23.163788333333333,
  "time_utc": "2026-07-19T05:04:59+00:00",
  "text": "KATERINA STAR (passenger) is stationary at 3 km off Spetses. Reported destination: SPETSES-KOSTA-SP/SES."
 },
 {
  "id": "status-237933900",
  "type": "vessel_status",
  "mmsi": 237933900,
  "name": "PANAGIA KOIMISIS",
  "lat": 37.98339166666666,
  "lon": 23.418525,
  "time_utc": "2026-07-19T05:04:59+00:00",
  "text": "PANAGIA KOIMISIS is stationary at open water (37.983, 23.419). Reported destination: FANEROMENI-MEGARA."
 },
 {
  "id": "status-240706600",
  "type": "vessel_status",
  "mmsi": 240706600,
  "name": "PILOT BOAT PY70",
  "lat": 37.91698833333333,
  "lon": 23.594753333333333,
  "time_utc": "2026-07-19T05:04:59+00:00",
  "text": "PILOT BOAT PY70 is underway at 22 knots near Piraeus anchorage, heading south."
 },
 {
  "id": "status-241435000",
  "type": "vessel_status",
  "mmsi": 241435000,
  "name": "SUPERFERRY",
  "lat": 38.023154999999996,
  "lon": 24.01199,
  "time_utc": "2026-07-19T05:04:59+00:00",
  "text": "SUPERFERRY (passenger) is stationary at Rafina. Reported destination: R-P-N-M-T-R."
 },
 {
  "id": "status-249965000",
  "type": "vessel_status",
  "mmsi": 249965000,
  "name": "MADIZ",
  "lat": 37.960119999999996,
  "lon": 23.571121666666667,
  "time_utc": "2026-07-19T05:04:59+00:00",
  "text": "MADIZ (pleasure) is moored at Perama. Reported destination: PERAMA."
 },
 {
  "id": "status-237002600",
  "type": "vessel_status",
  "mmsi": 237002600,
  "name": "APOLLON HELLAS",
  "lat": 37.90152333333333,
  "lon": 23.585665,
  "time_utc": "2026-07-19T05:04:59+00:00",
  "text": "APOLLON HELLAS (passenger) is underway at 14 knots near Piraeus anchorage, heading southwest. Reported destination: ARGOSARONIKOS."
 },
 {
  "id": "status-240259500",
  "type": "vessel_status",
  "mmsi": 240259500,
  "name": "COWBOYS",
  "lat": 37.931705,
  "lon": 23.684756666666665,
  "time_utc": "2026-07-19T05:04:59+00:00",
  "text": "COWBOYS (pleasure) is stationary at 4 km off Piraeus."
 },
 {
  "id": "status-241133000",
  "type": "vessel_status",
  "mmsi": 241133000,
  "name": "PANORAMA",
  "lat": 37.94439333333333,
  "lon": 23.641663333333334,
  "time_utc": "2026-07-19T05:04:59+00:00",
  "text": "PANORAMA (passenger) is stationary at Piraeus. Reported destination: PIR-AIG."
 },
 {
  "id": "status-241678000",
  "type": "vessel_status",
  "mmsi": 241678000,
  "name": "HIGHSPEED 3",
  "lat": 37.944915,
  "lon": 23.63819833333333,
  "time_utc": "2026-07-19T05:04:59+00:00",
  "text": "HIGHSPEED 3 (high-speed craft) is moored at Piraeus. Reported destination: GRPIR."
 },
 {
  "id": "status-237008100",
  "type": "vessel_status",
  "mmsi": 237008100,
  "name": "POSEIDONAS",
  "lat": 37.94466,
  "lon": 23.64148,
  "time_utc": "2026-07-19T05:04:59+00:00",
  "text": "POSEIDONAS (passenger) is stationary at Piraeus."
 },
 {
  "id": "status-240081400",
  "type": "vessel_status",
  "mmsi": 240081400,
  "name": "ZEN",
  "lat": 37.49907333333333,
  "lon": 23.450295,
  "time_utc": "2026-07-19T05:04:59+00:00",
  "text": "ZEN (pleasure) is underway at 1 knots near Poros, heading west. Reported destination: SARONIKOS."
 },
 {
  "id": "status-240110600",
  "type": "vessel_status",
  "mmsi": 240110600,
  "name": "AXION",
  "lat": 37.931873333333336,
  "lon": 23.684235,
  "time_utc": "2026-07-19T05:04:59+00:00",
  "text": "AXION (pleasure) is moored at 4 km off Piraeus."
 },
 {
  "id": "status-227910790",
  "type": "vessel_status",
  "mmsi": 227910790,
  "name": "DABCHICK",
  "lat": 37.913911666666664,
  "lon": 23.703,
  "time_utc": "2026-07-19T05:04:59+00:00",
  "text": "DABCHICK is stationary at 7 km off Piraeus."
 },
 {
  "id": "status-240639300",
  "type": "vessel_status",
  "mmsi": 240639300,
  "name": "AGGELIS F. III",
  "lat": 37.98623666666666,
  "lon": 23.41411,
  "time_utc": "2026-07-19T05:04:59+00:00",
  "text": "AGGELIS F. III (passenger) is underway at 7 knots near open water (37.986, 23.414), heading north. Reported destination: FANEROMENI-MEGARA."
 },
 {
  "id": "status-239546200",
  "type": "vessel_status",
  "mmsi": 239546200,
  "name": "KONSTANTINOS K",
  "lat": 37.965646666666665,
  "lon": 23.53054,
  "time_utc": "2026-07-19T05:04:59+00:00",
  "text": "KONSTANTINOS K (passenger) is stationary at Salamina (Paloukia). Reported destination: PERAMA-PALOUKIA."
 },
 {
  "id": "status-239958300",
  "type": "vessel_status",
  "mmsi": 239958300,
  "name": "PANFILO",
  "lat": 37.71397,
  "lon": 23.34710833333333,
  "time_utc": "2026-07-19T05:04:59+00:00",
  "text": "PANFILO (sailing) is stationary at 2 km off Agistri (Skala)."
 },
 {
  "id": "status-240098600",
  "type": "vessel_status",
  "mmsi": 240098600,
  "name": "PROTOPOROS XIV",
  "lat": 37.965941666666666,
  "lon": 23.530843333333333,
  "time_utc": "2026-07-19T05:04:59+00:00",
  "text": "PROTOPOROS XIV (passenger) is stationary at Salamina (Paloukia). Reported destination: PALOUKIA - PERAMA."
 },
 {
  "id": "status-210967000",
  "type": "vessel_status",
  "mmsi": 210967000,
  "name": "CHAMPIONSLEAGUE JET1",
  "lat": 37.94504,
  "lon": 23.63984,
  "time_utc": "2026-07-19T05:04:59+00:00",
  "text": "CHAMPIONSLEAGUE JET1 (high-speed craft) is moored at Piraeus. Reported destination: P-S-T-M-P-N-T-H."
 },
 {
  "id": "status-271001044",
  "type": "vessel_status",
  "mmsi": 271001044,
  "name": "BLACK SEA",
  "lat": 37.500301666666665,
  "lon": 23.451663333333332,
  "time_utc": "2026-07-19T05:04:59+00:00",
  "text": "BLACK SEA (pleasure) is moored at Poros. Reported destination: VOLIGMANI."
 },
 {
  "id": "status-240258700",
  "type": "vessel_status",
  "mmsi": 240258700,
  "name": "ALEXIA",
  "lat": 37.73768333333333,
  "lon": 23.834355000000002,
  "time_utc": "2026-07-19T05:04:59+00:00",
  "text": "ALEXIA (sailing) is underway at 5 knots near open water (37.738, 23.834), heading southeast."
 },
 {
  "id": "status-248365000",
  "type": "vessel_status",
  "mmsi": 248365000,
  "name": "OPTION B",
  "lat": 37.93013833333334,
  "lon": 23.68477,
  "time_utc": "2026-07-19T05:04:59+00:00",
  "text": "OPTION B (pleasure) is moored at 4 km off Piraeus. Reported destination: MARINA FLISVOS."
 },
 {
  "id": "status-240626600",
  "type": "vessel_status",
  "mmsi": 240626600,
  "name": "SAHANA",
  "lat": 37.26268,
  "lon": 23.162705000000003,
  "time_utc": "2026-07-19T05:04:59+00:00",
  "text": "SAHANA (sailing) is stationary at Spetses."
 },
 {
  "id": "status-241917000",
  "type": "vessel_status",
  "mmsi": 241917000,
  "name": "BENIK",
  "lat": 37.261833333333335,
  "lon": 23.164733333333334,
  "time_utc": "2026-07-19T05:04:59+00:00",
  "text": "BENIK (pleasure) is stationary at Spetses. Reported destination: AEGEAN SEA."
 },
 {
  "id": "status-240777000",
  "type": "vessel_status",
  "mmsi": 240777000,
  "name": "MABROUK",
  "lat": 37.930240000000005,
  "lon": 23.684540000000002,
  "time_utc": "2026-07-19T05:04:59+00:00",
  "text": "MABROUK (pleasure) is moored at 4 km off Piraeus. Reported destination: FLOISVOS."
 },
 {
  "id": "status-240780000",
  "type": "vessel_status",
  "mmsi": 240780000,
  "name": "FELIGO V",
  "lat": 37.94167166666667,
  "lon": 23.670066666666667,
  "time_utc": "2026-07-19T05:04:59+00:00",
  "text": "FELIGO V (pleasure) is moored at 3 km off Piraeus. Reported destination: MARINA ATHINON."
 },
 {
  "id": "status-229739000",
  "type": "vessel_status",
  "mmsi": 229739000,
  "name": "NATALIA V",
  "lat": 37.29419333333333,
  "lon": 23.160295,
  "time_utc": "2026-07-19T05:04:59+00:00",
  "text": "NATALIA V (pleasure) is at anchor at 3 km off Spetses. Reported destination: SARONIC."
 },
 {
  "id": "status-215000815",
  "type": "vessel_status",
  "mmsi": 215000815,
  "name": "FOUR SEVEN",
  "lat": 37.49926833333333,
  "lon": 23.45116,
  "time_utc": "2026-07-19T05:04:59+00:00",
  "text": "FOUR SEVEN (pleasure) is moored at Poros. Reported destination: ATHENS."
 },
 {
  "id": "status-249867000",
  "type": "vessel_status",
  "mmsi": 249867000,
  "name": "BLADE6",
  "lat": 37.94160333333333,
  "lon": 23.669061666666668,
  "time_utc": "2026-07-19T05:04:59+00:00",
  "text": "BLADE6 (pleasure) is stationary at 3 km off Piraeus. Reported destination: ATHENS MARINA."
 },
 {
  "id": "status-240544900",
  "type": "vessel_status",
  "mmsi": 240544900,
  "name": "ATALANTI",
  "lat": 37.939375000000005,
  "lon": 23.669386666666664,
  "time_utc": "2026-07-19T05:04:59+00:00",
  "text": "ATALANTI (pleasure) is moored at 3 km off Piraeus. Reported destination: PIRAEUS."
 },
 {
  "id": "status-239786000",
  "type": "vessel_status",
  "mmsi": 239786000,
  "name": "TALOS",
  "lat": 37.893375,
  "lon": 23.621268333333333,
  "time_utc": "2026-07-19T05:04:59+00:00",
  "text": "TALOS (cargo) is underway at 11 knots near 6 km off Piraeus, heading northwest. Reported destination: PIRAEUS."
 },
 {
  "id": "status-241443000",
  "type": "vessel_status",
  "mmsi": 241443000,
  "name": "PANTOKRATOR",
  "lat": 37.978854999999996,
  "lon": 23.547601666666665,
  "time_utc": "2026-07-19T05:04:59+00:00",
  "text": "PANTOKRATOR (special craft) is underway at 10 knots near 2 km off Salamina (Paloukia), heading north. Reported destination: GRPIR."
 },
 {
  "id": "status-240925000",
  "type": "vessel_status",
  "mmsi": 240925000,
  "name": "KARAPIPERIS NEW GENE",
  "lat": 37.95188333333333,
  "lon": 23.582483333333336,
  "time_utc": "2026-07-19T05:04:59+00:00",
  "text": "KARAPIPERIS NEW GENE (special craft) is underway at 8 knots near 2 km off Perama, heading west. Reported destination: PIRAEUS."
 },
 {
  "id": "status-319323400",
  "type": "vessel_status",
  "mmsi": 319323400,
  "name": "ASTRAEA",
  "lat": 37.80247833333333,
  "lon": 23.773728333333334,
  "time_utc": "2026-07-19T05:04:59+00:00",
  "text": "ASTRAEA (pleasure) is at anchor at open water (37.802, 23.774). Reported destination: VOULIAGMENI."
 },
 {
  "id": "status-249428000",
  "type": "vessel_status",
  "mmsi": 249428000,
  "name": "LARRIANE MAE",
  "lat": 37.243116666666666,
  "lon": 23.235586666666666,
  "time_utc": "2026-07-19T05:04:59+00:00",
  "text": "LARRIANE MAE (pleasure) is underway at 10 knots near 7 km off Spetses, heading southeast."
 },
 {
  "id": "status-256315000",
  "type": "vessel_status",
  "mmsi": 256315000,
  "name": "O'NEIRO",
  "lat": 37.26186166666666,
  "lon": 23.164076666666666,
  "time_utc": "2026-07-19T05:04:59+00:00",
  "text": "O'NEIRO (pleasure) is at anchor at Spetses. Reported destination: SARONIC."
 },
 {
  "id": "status-339000037",
  "type": "vessel_status",
  "mmsi": 339000037,
  "name": "INFINITY",
  "lat": 37.264646666666664,
  "lon": 23.16512,
  "time_utc": "2026-07-19T05:04:59+00:00",
  "text": "INFINITY (pleasure) is stationary at Spetses. Reported destination: SARONIKOS."
 },
 {
  "id": "status-636025516",
  "type": "vessel_status",
  "mmsi": 636025516,
  "name": "MINERVA GRACE",
  "lat": 37.94753,
  "lon": 23.55352,
  "time_utc": "2026-07-19T05:04:59+00:00",
  "text": "MINERVA GRACE (tanker) is moored at 2 km off Perama. Reported destination: FOR ORDERS."
 },
 {
  "id": "status-240917000",
  "type": "vessel_status",
  "mmsi": 240917000,
  "name": "VERNICOS MASTER",
  "lat": 38.03592166666667,
  "lon": 23.512598333333337,
  "time_utc": "2026-07-19T05:04:59+00:00",
  "text": "VERNICOS MASTER (special craft) is underway at 2 knots near Elefsis Bay anchorage, heading west."
 },
 {
  "id": "status-256004960",
  "type": "vessel_status",
  "mmsi": 256004960,
  "name": "EM-ES",
  "lat": 37.499905,
  "lon": 23.45106,
  "time_utc": "2026-07-19T05:04:59+00:00",
  "text": "EM-ES (pleasure) is stationary at Poros."
 },
 {
  "id": "status-241765000",
  "type": "vessel_status",
  "mmsi": 241765000,
  "name": "KASSANDRA",
  "lat": 37.91345166666667,
  "lon": 23.70423,
  "time_utc": "2026-07-19T05:04:59+00:00",
  "text": "KASSANDRA (pleasure) is moored at 7 km off Piraeus. Reported destination: ALIMOS."
 },
 {
  "id": "status-248099000",
  "type": "vessel_status",
  "mmsi": 248099000,
  "name": "JAGUAR II",
  "lat": 37.28062,
  "lon": 23.158138333333333,
  "time_utc": "2026-07-19T05:04:59+00:00",
  "text": "JAGUAR II (pleasure) is underway at 8 knots near 2 km off Spetses, heading west. Reported destination: POROS."
 },
 {
  "id": "status-237929800",
  "type": "vessel_status",
  "mmsi": 237929800,
  "name": "OXYGEN 8",
  "lat": 37.91405666666667,
  "lon": 23.702031666666667,
  "time_utc": "2026-07-19T05:04:59+00:00",
  "text": "OXYGEN 8 (pleasure) is stationary at 7 km off Piraeus."
 },
 {
  "id": "status-239982500",
  "type": "vessel_status",
  "mmsi": 239982500,
  "name": "NOVA",
  "lat": 37.93107666666666,
  "lon": 23.64808833333333,
  "time_utc": "2026-07-19T05:04:59+00:00",
  "text": "NOVA (pleasure) is moored at Piraeus. Reported destination: ZEA."
 },
 {
  "id": "status-304029000",
  "type": "vessel_status",
  "mmsi": 304029000,
  "name": "FINOLA M",
  "lat": 37.949795,
  "lon": 23.600255,
  "time_utc": "2026-07-19T05:04:59+00:00",
  "text": "FINOLA M (cargo) is moored at 3 km off Piraeus. Reported destination: GRPIR."
 },
 {
  "id": "status-240870000",
  "type": "vessel_status",
  "mmsi": 240870000,
  "name": "AEGEAN TIFFANY",
  "lat": 38.037596666666666,
  "lon": 23.532809999999998,
  "time_utc": "2026-07-19T05:04:59+00:00",
  "text": "AEGEAN TIFFANY (tanker) is stationary at Elefsina. Reported destination: PERIOXH."
 },
 {
  "id": "status-352002491",
  "type": "vessel_status",
  "mmsi": 352002491,
  "name": "MARILOU",
  "lat": 37.916518333333336,
  "lon": 23.559963333333332,
  "time_utc": "2026-07-19T05:04:59+00:00",
  "text": "MARILOU (cargo) is at anchor at Piraeus anchorage. Reported destination: GRPIR."
 },
 {
  "id": "status-240763900",
  "type": "vessel_status",
  "mmsi": 240763900,
  "name": "LODIRE",
  "lat": 37.73358666666666,
  "lon": 23.858208333333334,
  "time_utc": "2026-07-19T05:04:59+00:00",
  "text": "LODIRE (pleasure) is underway at 8 knots near open water (37.734, 23.858), heading southeast."
 },
 {
  "id": "status-255806063",
  "type": "vessel_status",
  "mmsi": 255806063,
  "name": "MSC MANON",
  "lat": 37.95643833333334,
  "lon": 23.599778333333333,
  "time_utc": "2026-07-19T05:04:59+00:00",
  "text": "MSC MANON (cargo) is underway at 4 knots near 3 km off Perama, heading southwest. Reported destination: GRPIR."
 },
 {
  "id": "status-247282810",
  "type": "vessel_status",
  "mmsi": 247282810,
  "name": "GENNY",
  "lat": 37.93804,
  "lon": 23.66726,
  "time_utc": "2026-07-19T05:04:59+00:00",
  "text": "GENNY is stationary at 3 km off Piraeus."
 },
 {
  "id": "status-248989000",
  "type": "vessel_status",
  "mmsi": 248989000,
  "name": "LADY G II",
  "lat": 37.93288333333333,
  "lon": 23.64765,
  "time_utc": "2026-07-19T05:04:59+00:00",
  "text": "LADY G II (pleasure) is moored at Piraeus. Reported destination: SARONIC."
 },
 {
  "id": "status-227568170",
  "type": "vessel_status",
  "mmsi": 227568170,
  "name": "KI MOR",
  "lat": 37.518343333333334,
  "lon": 23.398953333333335,
  "time_utc": "2026-07-19T05:04:59+00:00",
  "text": "KI MOR is stationary at 5 km off Poros."
 },
 {
  "id": "status-259044200",
  "type": "vessel_status",
  "mmsi": 259044200,
  "name": "S/Y AMARONE",
  "lat": 37.51219666666667,
  "lon": 23.442801666666664,
  "time_utc": "2026-07-19T05:04:59+00:00",
  "text": "S/Y AMARONE is stationary at 2 km off Poros."
 },
 {
  "id": "status-218055790",
  "type": "vessel_status",
  "mmsi": 218055790,
  "name": "ROSECCA",
  "lat": 37.49991833333333,
  "lon": 23.446109999999997,
  "time_utc": "2026-07-19T05:04:59+00:00",
  "text": "ROSECCA (sailing) is stationary at Poros."
 },
 {
  "id": "status-257704370",
  "type": "vessel_status",
  "mmsi": 257704370,
  "name": "CAREKA",
  "lat": 37.507825000000004,
  "lon": 23.40809,
  "time_utc": "2026-07-19T05:04:59+00:00",
  "text": "CAREKA is stationary at 4 km off Poros."
 },
 {
  "id": "status-240439300",
  "type": "vessel_status",
  "mmsi": 240439300,
  "name": "NOMMO",
  "lat": 37.93983,
  "lon": 23.668664999999997,
  "time_utc": "2026-07-19T05:04:59+00:00",
  "text": "NOMMO (sailing) is moored at 3 km off Piraeus. Reported destination: ATHENS MARINA."
 },
 {
  "id": "status-241967000",
  "type": "vessel_status",
  "mmsi": 241967000,
  "name": "LIBERDADE",
  "lat": 37.932750000000006,
  "lon": 23.681881666666666,
  "time_utc": "2026-07-19T05:04:59+00:00",
  "text": "LIBERDADE (pleasure) is stationary at 4 km off Piraeus. Reported destination: SARONIK."
 },
 {
  "id": "status-240040100",
  "type": "vessel_status",
  "mmsi": 240040100,
  "name": "GREY WOLF",
  "lat": 37.49952333333333,
  "lon": 23.45097666666667,
  "time_utc": "2026-07-19T05:04:59+00:00",
  "text": "GREY WOLF (pleasure) is at anchor at Poros. Reported destination: ZEA."
 },
 {
  "id": "status-237511800",
  "type": "vessel_status",
  "mmsi": 237511800,
  "name": "SONATA",
  "lat": 37.518998333333336,
  "lon": 23.403023333333334,
  "time_utc": "2026-07-19T05:04:59+00:00",
  "text": "SONATA is stationary at 5 km off Poros."
 },
 {
  "id": "status-319192000",
  "type": "vessel_status",
  "mmsi": 319192000,
  "name": "MARAYA",
  "lat": 37.47439,
  "lon": 23.557601666666667,
  "time_utc": "2026-07-19T05:04:59+00:00",
  "text": "MARAYA (pleasure) is underway at 13 knots near open water (37.474, 23.558), heading south. Reported destination: HYDRA."
 },
 {
  "id": "status-248033000",
  "type": "vessel_status",
  "mmsi": 248033000,
  "name": "EMERALD",
  "lat": 38.02461666666667,
  "lon": 23.5941,
  "time_utc": "2026-07-19T05:04:59+00:00",
  "text": "EMERALD (tanker) is moored at 5 km off Elefsina. Reported destination: GRASS."
 },
 {
  "id": "status-636020582",
  "type": "vessel_status",
  "mmsi": 636020582,
  "name": "ADMIRAL MOON",
  "lat": 37.907673333333335,
  "lon": 23.542334999999998,
  "time_utc": "2026-07-19T05:04:59+00:00",
  "text": "ADMIRAL MOON (cargo) is at anchor at Piraeus anchorage. Reported destination: PIRAEUS."
 },
 {
  "id": "status-237013400",
  "type": "vessel_status",
  "mmsi": 237013400,
  "name": "COSMOS",
  "lat": 37.910666666666664,
  "lon": 23.646684999999998,
  "time_utc": "2026-07-19T05:04:59+00:00",
  "text": "COSMOS (passenger) is underway at 13 knots near 4 km off Piraeus, heading southwest. Reported destination: SARONIKOS."
 },
 {
  "id": "status-249748000",
  "type": "vessel_status",
  "mmsi": 249748000,
  "name": "SOUTHWIND OF",
  "lat": 37.773,
  "lon": 23.741666666666667,
  "time_utc": "2026-07-19T05:04:59+00:00",
  "text": "SOUTHWIND OF (sailing) is underway at 10 knots near open water (37.773, 23.742), heading northeast. Reported destination: CRUISING."
 },
 {
  "id": "status-319775000",
  "type": "vessel_status",
  "mmsi": 319775000,
  "name": "SARAH",
  "lat": 37.92970666666667,
  "lon": 23.68167833333333,
  "time_utc": "2026-07-19T05:04:59+00:00",
  "text": "SARAH (pleasure) is moored at 4 km off Piraeus. Reported destination: FLISVOS."
 },
 {
  "id": "status-240045800",
  "type": "vessel_status",
  "mmsi": 240045800,
  "name": "PATHOS",
  "lat": 37.50022,
  "lon": 23.45116,
  "time_utc": "2026-07-19T05:04:59+00:00",
  "text": "PATHOS (pleasure) is stationary at Poros. Reported destination: ALIMOS."
 },
 {
  "id": "status-240205100",
  "type": "vessel_status",
  "mmsi": 240205100,
  "name": "LEGEND",
  "lat": 37.93737333333333,
  "lon": 23.68574,
  "time_utc": "2026-07-19T05:04:59+00:00",
  "text": "LEGEND is stationary at 4 km off Piraeus."
 },
 {
  "id": "status-240425400",
  "type": "vessel_status",
  "mmsi": 240425400,
  "name": "LADY L",
  "lat": 37.9619,
  "lon": 23.498583333333332,
  "time_utc": "2026-07-19T05:04:59+00:00",
  "text": "LADY L is stationary at 3 km off Salamina (Paloukia)."
 },
 {
  "id": "status-228475000",
  "type": "vessel_status",
  "mmsi": 228475000,
  "name": "MAGIC CAT",
  "lat": 37.858511666666665,
  "lon": 23.74089,
  "time_utc": "2026-07-19T05:04:59+00:00",
  "text": "MAGIC CAT is stationary at open water (37.859, 23.741)."
 },
 {
  "id": "status-238584540",
  "type": "vessel_status",
  "mmsi": 238584540,
  "name": "NURIA",
  "lat": 37.49917833333333,
  "lon": 23.44733,
  "time_utc": "2026-07-19T05:04:59+00:00",
  "text": "NURIA is stationary at Poros."
 },
 {
  "id": "status-319344500",
  "type": "vessel_status",
  "mmsi": 319344500,
  "name": "HALO",
  "lat": 37.933595,
  "lon": 23.648818333333335,
  "time_utc": "2026-07-19T05:04:59+00:00",
  "text": "HALO (pleasure) is moored at Piraeus. Reported destination: ZEAS."
 },
 {
  "id": "status-228062750",
  "type": "vessel_status",
  "mmsi": 228062750,
  "name": "MALO",
  "lat": 37.50035333333334,
  "lon": 23.444993333333333,
  "time_utc": "2026-07-19T05:04:59+00:00",
  "text": "MALO is stationary at Poros."
 },
 {
  "id": "status-240724600",
  "type": "vessel_status",
  "mmsi": 240724600,
  "name": "ALMOSTA ROAD",
  "lat": 37.93534666666667,
  "lon": 23.648508333333332,
  "time_utc": "2026-07-19T05:04:59+00:00",
  "text": "ALMOSTA ROAD is stationary at Piraeus."
 },
 {
  "id": "status-240755200",
  "type": "vessel_status",
  "mmsi": 240755200,
  "name": "AETHERIA",
  "lat": 37.83085166666667,
  "lon": 23.7316,
  "time_utc": "2026-07-19T05:04:59+00:00",
  "text": "AETHERIA is underway at 8 knots near open water (37.831, 23.732), heading southeast."
 },
 {
  "id": "status-240588500",
  "type": "vessel_status",
  "mmsi": 240588500,
  "name": "BABALU",
  "lat": 37.46249833333333,
  "lon": 23.51954,
  "time_utc": "2026-07-19T05:04:59+00:00",
  "text": "BABALU is underway at 8 knots near 7 km off Poros, heading southeast."
 },
 {
  "id": "status-352001667",
  "type": "vessel_status",
  "mmsi": 352001667,
  "name": "BULLISH",
  "lat": 37.938026666666666,
  "lon": 23.649276666666665,
  "time_utc": "2026-07-19T05:04:59+00:00",
  "text": "BULLISH is stationary at Piraeus."
 },
 {
  "id": "status-237001000",
  "type": "vessel_status",
  "mmsi": 237001000,
  "name": "SUPERSTAR",
  "lat": 38.022346666666664,
  "lon": 24.01185333333333,
  "time_utc": "2026-07-19T05:04:59+00:00",
  "text": "SUPERSTAR (passenger) is stationary at Rafina. Reported destination: JMK-TIN-AND-RAF."
 },
 {
  "id": "status-227252510",
  "type": "vessel_status",
  "mmsi": 227252510,
  "name": "SWING OUT",
  "lat": 37.504223333333336,
  "lon": 23.44865,
  "time_utc": "2026-07-19T05:04:59+00:00",
  "text": "SWING OUT is stationary at Poros."
 },
 {
  "id": "status-354409000",
  "type": "vessel_status",
  "mmsi": 354409000,
  "name": "STELLAR",
  "lat": 37.900713333333336,
  "lon": 23.539021666666667,
  "time_utc": "2026-07-19T05:04:59+00:00",
  "text": "STELLAR (tanker) is underway at 1 knots near Piraeus anchorage, heading northwest. Reported destination: GRAGT."
 },
 {
  "id": "status-311000706",
  "type": "vessel_status",
  "mmsi": 311000706,
  "name": "IRINI",
  "lat": 38.024413333333335,
  "lon": 23.516763333333333,
  "time_utc": "2026-07-19T05:04:59+00:00",
  "text": "IRINI is at anchor at Elefsis Bay anchorage."
 },
 {
  "id": "status-304347000",
  "type": "vessel_status",
  "mmsi": 304347000,
  "name": "OCEAN CONNECTOR",
  "lat": 37.632533333333335,
  "lon": 24.034195,
  "time_utc": "2026-07-19T05:04:59+00:00",
  "text": "OCEAN CONNECTOR is underway at 8 knots near open water (37.633, 24.034), heading southwest."
 },
 {
  "id": "status-232026670",
  "type": "vessel_status",
  "mmsi": 232026670,
  "name": "CHARM_SPIRIT",
  "lat": 38.02513666666667,
  "lon": 23.59399,
  "time_utc": "2026-07-19T05:04:59+00:00",
  "text": "CHARM_SPIRIT (tanker) is moored at 5 km off Elefsina. Reported destination: ASS GR."
 },
 {
  "id": "status-538010485",
  "type": "vessel_status",
  "mmsi": 538010485,
  "name": "VENTO DI BORA",
  "lat": 37.94785,
  "lon": 23.594715,
  "time_utc": "2026-07-19T05:04:59+00:00",
  "text": "VENTO DI BORA (cargo) is underway at 5 knots near 3 km off Perama, heading southeast. Reported destination: GRPIR-CYLMS."
 },
 {
  "id": "status-636021518",
  "type": "vessel_status",
  "mmsi": 636021518,
  "name": "MSC CALEDONIA II",
  "lat": 37.52838666666666,
  "lon": 23.685693333333333,
  "time_utc": "2026-07-19T05:04:59+00:00",
  "text": "MSC CALEDONIA II (cargo) is underway at 0 knots near open water (37.528, 23.686), heading northeast. Reported destination: GRPIR."
 },
 {
  "id": "status-241620000",
  "type": "vessel_status",
  "mmsi": 241620000,
  "name": "AQUA BLUE",
  "lat": 37.71252666666667,
  "lon": 24.078719999999997,
  "time_utc": "2026-07-19T05:04:59+00:00",
  "text": "AQUA BLUE is underway at 16 knots near 2 km off Lavrio, heading northeast."
 },
 {
  "id": "status-241918000",
  "type": "vessel_status",
  "mmsi": 241918000,
  "name": "DALOLI",
  "lat": 37.581541666666666,
  "lon": 23.484741666666665,
  "time_utc": "2026-07-19T05:04:59+00:00",
  "text": "DALOLI (pleasure) is underway at 12 knots near open water (37.582, 23.485), heading southeast. Reported destination: ALIMOS."
 },
 {
  "id": "status-210989000",
  "type": "vessel_status",
  "mmsi": 210989000,
  "name": "IONIA",
  "lat": 37.656821666666666,
  "lon": 23.719275,
  "time_utc": "2026-07-19T05:04:59+00:00",
  "text": "IONIA (cargo) is underway at 13 knots near open water (37.657, 23.719), heading southeast. Reported destination: GRPIR."
 },
 {
  "id": "status-240492700",
  "type": "vessel_status",
  "mmsi": 240492700,
  "name": "AELIA",
  "lat": 37.844609999999996,
  "lon": 23.47268,
  "time_utc": "2026-07-19T05:04:59+00:00",
  "text": "AELIA is underway at 6 knots near open water (37.845, 23.473), heading south."
 },
 {
  "id": "status-240685500",
  "type": "vessel_status",
  "mmsi": 240685500,
  "name": "SUNNY DREAM",
  "lat": 37.26222666666667,
  "lon": 23.163486666666664,
  "time_utc": "2026-07-19T05:04:59+00:00",
  "text": "SUNNY DREAM (pleasure) is stationary at Spetses."
 },
 {
  "id": "status-256004007",
  "type": "vessel_status",
  "mmsi": 256004007,
  "name": "ZIA SPEED",
  "lat": 37.76658333333333,
  "lon": 23.414673333333333,
  "time_utc": "2026-07-19T05:04:59+00:00",
  "text": "ZIA SPEED is underway at 13 knots near 3 km off Aegina, heading northeast."
 },
 {
  "id": "status-237128700",
  "type": "vessel_status",
  "mmsi": 237128700,
  "name": "MARIA T",
  "lat": 38.03605166666667,
  "lon": 23.55193166666667,
  "time_utc": "2026-07-19T05:04:59+00:00",
  "text": "MARIA T (cargo) is stationary at Elefsina. Reported destination: EEU."
 },
 {
  "id": "status-240040300",
  "type": "vessel_status",
  "mmsi": 240040300,
  "name": "CHARLIE",
  "lat": 37.51596333333334,
  "lon": 23.421118333333332,
  "time_utc": "2026-07-19T05:04:59+00:00",
  "text": "CHARLIE is underway at 6 knots near 3 km off Poros, heading southeast."
 },
 {
  "id": "status-256001513",
  "type": "vessel_status",
  "mmsi": 256001513,
  "name": "BLUE PEARL I",
  "lat": 37.931925,
  "lon": 23.683956666666667,
  "time_utc": "2026-07-19T05:04:59+00:00",
  "text": "BLUE PEARL I is stationary at 4 km off Piraeus."
 },
 {
  "id": "status-240761400",
  "type": "vessel_status",
  "mmsi": 240761400,
  "name": "CORALI",
  "lat": 37.69242166666667,
  "lon": 23.42988,
  "time_utc": "2026-07-19T05:04:59+00:00",
  "text": "CORALI is stationary at 6 km off Aegina."
 },
 {
  "id": "status-319354400",
  "type": "vessel_status",
  "mmsi": 319354400,
  "name": "MARALA",
  "lat": 37.93311333333334,
  "lon": 23.648554999999998,
  "time_utc": "2026-07-19T05:04:59+00:00",
  "text": "MARALA (pleasure) is moored at Piraeus. Reported destination: ATHENS."
 },
 {
  "id": "status-241756000",
  "type": "vessel_status",
  "mmsi": 241756000,
  "name": "KIMATA",
  "lat": 37.93789833333334,
  "lon": 23.648071666666667,
  "time_utc": "2026-07-19T05:04:59+00:00",
  "text": "KIMATA (sailing) is moored at Piraeus."
 },
 {
  "id": "status-248373000",
  "type": "vessel_status",
  "mmsi": 248373000,
  "name": "AMAZING GRACE",
  "lat": 37.93355666666666,
  "lon": 23.679658333333336,
  "time_utc": "2026-07-19T05:04:59+00:00",
  "text": "AMAZING GRACE is stationary at 4 km off Piraeus."
 },
 {
  "id": "status-239112700",
  "type": "vessel_status",
  "mmsi": 239112700,
  "name": "SUNCOCO",
  "lat": 37.49856666666667,
  "lon": 23.573458333333335,
  "time_utc": "2026-07-19T05:04:59+00:00",
  "text": "SUNCOCO (pleasure) is underway at 10 knots near open water (37.499, 23.573), heading north. Reported destination: KITHIRA."
 },
 {
  "id": "status-239800500",
  "type": "vessel_status",
  "mmsi": 239800500,
  "name": "BUBBLY",
  "lat": 37.93307,
  "lon": 23.6799,
  "time_utc": "2026-07-19T05:04:59+00:00",
  "text": "BUBBLY (pleasure) is stationary at 4 km off Piraeus. Reported destination: FLISVOS."
 },
 {
  "id": "status-636024506",
  "type": "vessel_status",
  "mmsi": 636024506,
  "name": "MSC COTE D'IVOIRE",
  "lat": 37.940865,
  "lon": 23.603028333333334,
  "time_utc": "2026-07-19T05:04:59+00:00",
  "text": "MSC COTE D'IVOIRE (cargo) is underway at 5 knots near 3 km off Piraeus, heading southeast. Reported destination: GRPIR."
 },
 {
  "id": "status-240775200",
  "type": "vessel_status",
  "mmsi": 240775200,
  "name": "VOGUEO",
  "lat": 37.50047166666666,
  "lon": 23.451958333333334,
  "time_utc": "2026-07-19T05:04:59+00:00",
  "text": "VOGUEO is stationary at Poros."
 },
 {
  "id": "status-241025000",
  "type": "vessel_status",
  "mmsi": 241025000,
  "name": "ERMIONI",
  "lat": 38.032853333333335,
  "lon": 23.531698333333335,
  "time_utc": "2026-07-19T05:04:59+00:00",
  "text": "ERMIONI (tanker) is at anchor at Elefsina. Reported destination: GRELE."
 },
 {
  "id": "status-261006197",
  "type": "vessel_status",
  "mmsi": 261006197,
  "name": "LA LOCA",
  "lat": 37.86653,
  "lon": 23.605743333333333,
  "time_utc": "2026-07-19T05:04:59+00:00",
  "text": "LA LOCA is underway at 5 knots near open water (37.867, 23.606), heading southwest."
 },
 {
  "id": "status-636022191",
  "type": "vessel_status",
  "mmsi": 636022191,
  "name": "ROSE I",
  "lat": 38.01828666666667,
  "lon": 23.569296666666666,
  "time_utc": "2026-07-19T05:04:59+00:00",
  "text": "ROSE I (tanker) is at anchor at 3 km off Elefsina. Reported destination: GR PIR."
 },
 {
  "id": "status-240967000",
  "type": "vessel_status",
  "mmsi": 240967000,
  "name": "DRAGON",
  "lat": 37.913734999999996,
  "lon": 23.704263333333333,
  "time_utc": "2026-07-19T05:04:59+00:00",
  "text": "DRAGON (pleasure) is stationary at 7 km off Piraeus. Reported destination: SARONIC."
 },
 {
  "id": "status-248223000",
  "type": "vessel_status",
  "mmsi": 248223000,
  "name": "HOW MUCH IS ENOUGH",
  "lat": 37.29376166666667,
  "lon": 23.18981,
  "time_utc": "2026-07-19T05:04:59+00:00",
  "text": "HOW MUCH IS ENOUGH (pleasure) is at anchor at 4 km off Spetses. Reported destination: PORTO HELI."
 },
 {
  "id": "status-319266000",
  "type": "vessel_status",
  "mmsi": 319266000,
  "name": "ASAHI",
  "lat": 37.93083,
  "lon": 23.680815,
  "time_utc": "2026-07-19T05:04:59+00:00",
  "text": "ASAHI (sailing) is stationary at 4 km off Piraeus. Reported destination: ATHENS."
 },
 {
  "id": "status-241696000",
  "type": "vessel_status",
  "mmsi": 241696000,
  "name": "MIA ZOI",
  "lat": 37.93382,
  "lon": 23.649068333333332,
  "time_utc": "2026-07-19T05:04:59+00:00",
  "text": "MIA ZOI (pleasure) is stationary at Piraeus. Reported destination: ZEA."
 },
 {
  "id": "status-538071582",
  "type": "vessel_status",
  "mmsi": 538071582,
  "name": "TYCHE",
  "lat": 37.850204999999995,
  "lon": 23.718194999999998,
  "time_utc": "2026-07-19T05:04:59+00:00",
  "text": "TYCHE is underway at 15 knots near open water (37.850, 23.718), heading northwest."
 },
 {
  "id": "status-207842570",
  "type": "vessel_status",
  "mmsi": 207842570,
  "name": "ANGEL",
  "lat": 37.518211666666666,
  "lon": 23.434336666666663,
  "time_utc": "2026-07-19T05:04:59+00:00",
  "text": "ANGEL is stationary at 3 km off Poros."
 },
 {
  "id": "status-319718000",
  "type": "vessel_status",
  "mmsi": 319718000,
  "name": "VAVA",
  "lat": 37.740825,
  "lon": 23.423268333333333,
  "time_utc": "2026-07-19T05:04:59+00:00",
  "text": "VAVA (pleasure) is at anchor at Aegina. Reported destination: AEGINA."
 },
 {
  "id": "status-636020898",
  "type": "vessel_status",
  "mmsi": 636020898,
  "name": "MSC DORINE V",
  "lat": 37.89421,
  "lon": 23.58893,
  "time_utc": "2026-07-19T05:04:59+00:00",
  "text": "MSC DORINE V is underway at 2 knots near Piraeus anchorage, heading north."
 },
 {
  "id": "status-229000277",
  "type": "vessel_status",
  "mmsi": 229000277,
  "name": "NAMELESS",
  "lat": 37.50044833333333,
  "lon": 23.451855000000002,
  "time_utc": "2026-07-19T05:04:59+00:00",
  "text": "NAMELESS is stationary at Poros."
 },
 {
  "id": "status-240600600",
  "type": "vessel_status",
  "mmsi": 240600600,
  "name": "ECLIPSE",
  "lat": 37.913485,
  "lon": 23.701181666666667,
  "time_utc": "2026-07-19T05:04:59+00:00",
  "text": "ECLIPSE is stationary at 7 km off Piraeus."
 },
 {
  "id": "status-538071196",
  "type": "vessel_status",
  "mmsi": 538071196,
  "name": "HOME",
  "lat": 37.931580000000004,
  "lon": 23.650183333333334,
  "time_utc": "2026-07-19T05:04:59+00:00",
  "text": "HOME (pleasure) is moored at Piraeus. Reported destination: ATHENS."
 },
 {
  "id": "status-249447000",
  "type": "vessel_status",
  "mmsi": 249447000,
  "name": "ATHENA I",
  "lat": 37.93120666666667,
  "lon": 23.683471666666666,
  "time_utc": "2026-07-19T05:04:59+00:00",
  "text": "ATHENA I (pleasure) is stationary at 4 km off Piraeus."
 },
 {
  "id": "status-237592700",
  "type": "vessel_status",
  "mmsi": 237592700,
  "name": "AIAKOS",
  "lat": 37.95890166666666,
  "lon": 23.540836666666667,
  "time_utc": "2026-07-19T05:04:59+00:00",
  "text": "AIAKOS (passenger) is underway at 8 knots near 1 km off Salamina (Paloukia), heading east. Reported destination: PALOUKIA  -  PERAMA."
 },
 {
  "id": "status-319273800",
  "type": "vessel_status",
  "mmsi": 319273800,
  "name": "ONE",
  "lat": 37.81090666666667,
  "lon": 23.766045000000002,
  "time_utc": "2026-07-19T05:04:59+00:00",
  "text": "ONE is stationary at open water (37.811, 23.766)."
 },
 {
  "id": "status-247484900",
  "type": "vessel_status",
  "mmsi": 247484900,
  "name": "ITAL WAY",
  "lat": 37.95662166666667,
  "lon": 23.588218333333334,
  "time_utc": "2026-07-19T05:04:59+00:00",
  "text": "ITAL WAY (cargo) is moored at 2 km off Perama. Reported destination: IL ASH > GR PIR."
 },
 {
  "id": "status-371559000",
  "type": "vessel_status",
  "mmsi": 371559000,
  "name": "TIANJIN HIGHWAY",
  "lat": 37.885729999999995,
  "lon": 23.52526,
  "time_utc": "2026-07-19T05:04:59+00:00",
  "text": "TIANJIN HIGHWAY (cargo) is at anchor at Piraeus anchorage. Reported destination: GRPIR."
 },
 {
  "id": "status-227000510",
  "type": "vessel_status",
  "mmsi": 227000510,
  "name": "POUSSIERE DETOILE",
  "lat": 37.50650333333333,
  "lon": 23.464074999999998,
  "time_utc": "2026-07-19T05:04:59+00:00",
  "text": "POUSSIERE DETOILE is stationary at Poros."
 },
 {
  "id": "status-240039900",
  "type": "vessel_status",
  "mmsi": 240039900,
  "name": "BRAVO",
  "lat": 37.51940666666667,
  "lon": 23.403663333333334,
  "time_utc": "2026-07-19T05:04:59+00:00",
  "text": "BRAVO (sailing) is moored at 5 km off Poros."
 },
 {
  "id": "status-240146300",
  "type": "vessel_status",
  "mmsi": 240146300,
  "name": "ALEGRIA",
  "lat": 37.911786666666664,
  "lon": 23.705023333333333,
  "time_utc": "2026-07-19T05:04:59+00:00",
  "text": "ALEGRIA (sailing) is stationary at 7 km off Piraeus."
 },
 {
  "id": "status-256839000",
  "type": "vessel_status",
  "mmsi": 256839000,
  "name": "ZIA",
  "lat": 37.7639,
  "lon": 23.412415,
  "time_utc": "2026-07-19T05:04:59+00:00",
  "text": "ZIA is underway at 13 knots near 2 km off Aegina, heading north."
 },
 {
  "id": "status-636021246",
  "type": "vessel_status",
  "mmsi": 636021246,
  "name": "MSC PAMIRA III",
  "lat": 37.468356666666665,
  "lon": 23.741521666666664,
  "time_utc": "2026-07-19T05:04:59+00:00",
  "text": "MSC PAMIRA III (cargo) is stationary at open water (37.468, 23.742). Reported destination: PIRAEUS."
 },
 {
  "id": "status-240152200",
  "type": "vessel_status",
  "mmsi": 240152200,
  "name": "MEGALO",
  "lat": 37.913761666666666,
  "lon": 23.705781666666667,
  "time_utc": "2026-07-19T05:04:59+00:00",
  "text": "MEGALO (sailing) is stationary at 7 km off Piraeus."
 },
 {
  "id": "status-636024014",
  "type": "vessel_status",
  "mmsi": 636024014,
  "name": "MSC EAGLE III",
  "lat": 37.608675,
  "lon": 23.630736666666667,
  "time_utc": "2026-07-19T05:04:59+00:00",
  "text": "MSC EAGLE III (cargo) is underway at 1 knots near open water (37.609, 23.631), heading east. Reported destination: GRPIR."
 },
 {
  "id": "status-256873000",
  "type": "vessel_status",
  "mmsi": 256873000,
  "name": "HANI I",
  "lat": 37.272013333333334,
  "lon": 23.152131666666666,
  "time_utc": "2026-07-19T05:04:59+00:00",
  "text": "HANI I is stationary at Spetses."
 },
 {
  "id": "status-240323600",
  "type": "vessel_status",
  "mmsi": 240323600,
  "name": "THALASSA",
  "lat": 37.49983833333333,
  "lon": 23.450831666666666,
  "time_utc": "2026-07-19T05:04:59+00:00",
  "text": "THALASSA (passenger) is moored at Poros. Reported destination: POROS."
 },
 {
  "id": "status-219024802",
  "type": "vessel_status",
  "mmsi": 219024802,
  "name": "ATHENE",
  "lat": 37.27122,
  "lon": 23.151439999999997,
  "time_utc": "2026-07-19T05:04:59+00:00",
  "text": "ATHENE is stationary at Spetses."
 },
 {
  "id": "status-227111530",
  "type": "vessel_status",
  "mmsi": 227111530,
  "name": "DJAM 2",
  "lat": 37.498171666666664,
  "lon": 23.454673333333336,
  "time_utc": "2026-07-19T05:04:59+00:00",
  "text": "DJAM 2 is stationary at Poros."
 },
 {
  "id": "status-630001257",
  "type": "vessel_status",
  "mmsi": 630001257,
  "name": "KARABAKH HEROES",
  "lat": 37.911325000000005,
  "lon": 23.11075,
  "time_utc": "2026-07-19T05:04:59+00:00",
  "text": "KARABAKH HEROES is at anchor at open water (37.911, 23.111)."
 },
 {
  "id": "status-240657800",
  "type": "vessel_status",
  "mmsi": 240657800,
  "name": "EFFIE STAR",
  "lat": 37.46157166666667,
  "lon": 23.517843333333335,
  "time_utc": "2026-07-19T05:04:59+00:00",
  "text": "EFFIE STAR is underway at 8 knots near 7 km off Poros, heading southeast."
 },
 {
  "id": "status-246659000",
  "type": "vessel_status",
  "mmsi": 246659000,
  "name": "HAPPY DELTA",
  "lat": 37.882571666666664,
  "lon": 23.53879166666667,
  "time_utc": "2026-07-19T05:04:59+00:00",
  "text": "HAPPY DELTA (cargo) is at anchor at Piraeus anchorage. Reported destination: GRPIR."
 },
 {
  "id": "status-215715000",
  "type": "vessel_status",
  "mmsi": 215715000,
  "name": "BLUE II",
  "lat": 37.931325,
  "lon": 23.64942166666667,
  "time_utc": "2026-07-19T05:04:59+00:00",
  "text": "BLUE II (pleasure) is moored at Piraeus. Reported destination: GR ATH."
 },
 {
  "id": "status-256586000",
  "type": "vessel_status",
  "mmsi": 256586000,
  "name": "O'MADELEINE",
  "lat": 37.93272,
  "lon": 23.647994999999998,
  "time_utc": "2026-07-19T05:04:59+00:00",
  "text": "O'MADELEINE (pleasure) is stationary at Piraeus. Reported destination: MARINA ZEAS."
 },
 {
  "id": "status-319005300",
  "type": "vessel_status",
  "mmsi": 319005300,
  "name": "SEADAR",
  "lat": 37.932685,
  "lon": 23.681936666666665,
  "time_utc": "2026-07-19T05:04:59+00:00",
  "text": "SEADAR is stationary at 4 km off Piraeus."
 },
 {
  "id": "status-256846000",
  "type": "vessel_status",
  "mmsi": 256846000,
  "name": "HOKULANI",
  "lat": 37.931846666666665,
  "lon": 23.680045,
  "time_utc": "2026-07-19T05:04:59+00:00",
  "text": "HOKULANI (pleasure) is moored at 4 km off Piraeus. Reported destination: FLISVOS."
 },
 {
  "id": "status-319271800",
  "type": "vessel_status",
  "mmsi": 319271800,
  "name": "KATHRYN",
  "lat": 37.693036666666664,
  "lon": 23.426446666666667,
  "time_utc": "2026-07-19T05:04:59+00:00",
  "text": "KATHRYN (pleasure) is underway at 7 knots near 6 km off Aegina, heading southwest. Reported destination: MONI."
 },
 {
  "id": "status-239433300",
  "type": "vessel_status",
  "mmsi": 239433300,
  "name": "SLOW LIVE",
  "lat": 37.86644166666667,
  "lon": 23.661498333333334,
  "time_utc": "2026-07-19T05:04:59+00:00",
  "text": "SLOW LIVE is underway at 11 knots near open water (37.866, 23.661), heading northeast."
 },
 {
  "id": "status-248870000",
  "type": "vessel_status",
  "mmsi": 248870000,
  "name": "LOUTRO",
  "lat": 37.908635,
  "lon": 23.07441,
  "time_utc": "2026-07-19T05:04:59+00:00",
  "text": "LOUTRO is at anchor at 6 km off Corinth Canal (Isthmia)."
 },
 {
  "id": "status-229842000",
  "type": "vessel_status",
  "mmsi": 229842000,
  "name": "CMA CGM BARRACUDA",
  "lat": 37.953851666666665,
  "lon": 23.586155,
  "time_utc": "2026-07-19T05:04:59+00:00",
  "text": "CMA CGM BARRACUDA (cargo) is moored at 2 km off Perama. Reported destination: GRPIR."
 },
 {
  "id": "status-237810700",
  "type": "vessel_status",
  "mmsi": 237810700,
  "name": "LET IT BE",
  "lat": 37.261741666666666,
  "lon": 23.164238333333333,
  "time_utc": "2026-07-19T05:04:59+00:00",
  "text": "LET IT BE (pleasure) is stationary at Spetses. Reported destination: ALIMOS."
 },
 {
  "id": "status-240381000",
  "type": "vessel_status",
  "mmsi": 240381000,
  "name": "PANDION",
  "lat": 37.93223,
  "lon": 23.682268333333333,
  "time_utc": "2026-07-19T05:04:59+00:00",
  "text": "PANDION (pleasure) is stationary at 4 km off Piraeus. Reported destination: FLISVOS."
 },
 {
  "id": "status-240483400",
  "type": "vessel_status",
  "mmsi": 240483400,
  "name": "TIGRA",
  "lat": 37.93002333333333,
  "lon": 23.684900000000003,
  "time_utc": "2026-07-19T05:04:59+00:00",
  "text": "TIGRA is stationary at 4 km off Piraeus."
 },
 {
  "id": "status-237365500",
  "type": "vessel_status",
  "mmsi": 237365500,
  "name": "ALEXANDROS M",
  "lat": 37.96379,
  "lon": 23.555205,
  "time_utc": "2026-07-19T05:04:59+00:00",
  "text": "ALEXANDROS M (passenger) is underway at 1 knots near 1 km off Perama. Reported destination: PERAMA   PALOUKIA."
 },
 {
  "id": "status-229140000",
  "type": "vessel_status",
  "mmsi": 229140000,
  "name": "VENTUM MARIS",
  "lat": 37.932338333333334,
  "lon": 23.650205000000003,
  "time_utc": "2026-07-19T05:04:59+00:00",
  "text": "VENTUM MARIS (pleasure) is underway at 2 knots near Piraeus, heading west. Reported destination: ZEA MARINA."
 },
 {
  "id": "status-229785000",
  "type": "vessel_status",
  "mmsi": 229785000,
  "name": "OCEAN PARADISE",
  "lat": 37.92932,
  "lon": 23.682341666666666,
  "time_utc": "2026-07-19T05:04:59+00:00",
  "text": "OCEAN PARADISE is moored at 4 km off Piraeus."
 },
 {
  "id": "status-310610000",
  "type": "vessel_status",
  "mmsi": 310610000,
  "name": "AZURA",
  "lat": 37.93934333333333,
  "lon": 23.633361666666666,
  "time_utc": "2026-07-19T05:04:59+00:00",
  "text": "AZURA (passenger) is moored at Piraeus. Reported destination: GRSDH > GRPIR."
 },
 {
  "id": "status-636021691",
  "type": "vessel_status",
  "mmsi": 636021691,
  "name": "KRITI CAPTAIN",
  "lat": 37.836533333333335,
  "lon": 23.46215,
  "time_utc": "2026-07-19T05:04:59+00:00",
  "text": "KRITI CAPTAIN is underway at 11 knots near 8 km off Souvala, heading west."
 },
 {
  "id": "status-248554000",
  "type": "vessel_status",
  "mmsi": 248554000,
  "name": "SEAVIOLET",
  "lat": 37.793885,
  "lon": 23.681896666666667,
  "time_utc": "2026-07-19T05:04:59+00:00",
  "text": "SEAVIOLET is underway at 10 knots near open water (37.794, 23.682), heading northwest."
 },
 {
  "id": "status-240706900",
  "type": "vessel_status",
  "mmsi": 240706900,
  "name": "PILOT BOAT PY73",
  "lat": 37.94696333333333,
  "lon": 23.594389999999997,
  "time_utc": "2026-07-19T05:04:59+00:00",
  "text": "PILOT BOAT PY73 is underway at 17 knots near 3 km off Perama, heading northwest."
 },
 {
  "id": "status-352003673",
  "type": "vessel_status",
  "mmsi": 352003673,
  "name": "KOCATEPE",
  "lat": 37.99792333333333,
  "lon": 23.545988333333334,
  "time_utc": "2026-07-19T05:04:59+00:00",
  "text": "KOCATEPE is underway at 6 knots near 4 km off Salamina (Paloukia), heading north."
 },
 {
  "id": "status-211736390",
  "type": "vessel_status",
  "mmsi": 211736390,
  "name": "MAPANI",
  "lat": 37.51719166666667,
  "lon": 23.39635333333333,
  "time_utc": "2026-07-19T05:04:59+00:00",
  "text": "MAPANI is stationary at 6 km off Poros."
 },
 {
  "id": "status-240531100",
  "type": "vessel_status",
  "mmsi": 240531100,
  "name": "ELLY",
  "lat": 37.81567,
  "lon": 23.810791666666667,
  "time_utc": "2026-07-19T05:04:59+00:00",
  "text": "ELLY is moored at open water (37.816, 23.811)."
 },
 {
  "id": "status-240790300",
  "type": "vessel_status",
  "mmsi": 240790300,
  "name": "ALIKI",
  "lat": 37.861446666666666,
  "lon": 23.707958333333334,
  "time_utc": "2026-07-19T05:04:59+00:00",
  "text": "ALIKI is underway at 7 knots near open water (37.861, 23.708), heading south."
 },
 {
  "id": "status-255806210",
  "type": "vessel_status",
  "mmsi": 255806210,
  "name": "WORLD TRAVELLER",
  "lat": 37.49961333333333,
  "lon": 23.811238333333332,
  "time_utc": "2026-07-19T05:04:59+00:00",
  "text": "WORLD TRAVELLER is underway at 11 knots near open water (37.500, 23.811), heading southwest."
 },
 {
  "id": "status-341900000",
  "type": "vessel_status",
  "mmsi": 341900000,
  "name": "BIEN",
  "lat": 37.74255,
  "lon": 23.707351666666668,
  "time_utc": "2026-07-19T05:04:59+00:00",
  "text": "BIEN is underway at 9 knots near open water (37.743, 23.707), heading northwest."
 },
 {
  "id": "status-351790000",
  "type": "vessel_status",
  "mmsi": 351790000,
  "name": "PARAGON",
  "lat": 37.72240333333333,
  "lon": 23.72568,
  "time_utc": "2026-07-19T05:04:59+00:00",
  "text": "PARAGON (cargo) is underway at 8 knots near open water (37.722, 23.726), heading northwest. Reported destination: GR ELE."
 },
 {
  "id": "status-710001634",
  "type": "vessel_status",
  "mmsi": 710001634,
  "name": "",
  "lat": 37.861401666666666,
  "lon": 23.723541666666666,
  "time_utc": "2026-07-19T05:04:59+00:00",
  "text": "MMSI 710001634 is underway at 6 knots near open water (37.861, 23.724), heading west."
 }
]